{"generated_at": "2026-07-01T23:03:39.055746+00:00", "orders": [{"ticker": "KXWCSOA-26JUL01USABIH-USAMTILLM10", "side": "no", "price": 45, "remaining_count": 349.0, "created_time": "2026-07-01T23:03:09.61141Z", "game": "USABIH", "team": "USA", "total": null, "stat_type": "soa", "lastname": "TILLM", "full_name": "Malik Tillman", "proj_min": 85.0, "pks": null, "prob": 62.42, "prob_no": 62.42, "prob_yes": 37.58, "roi_pct": 38.7, "matched_dollars_no": null, "matched_avg_price_no": null, "matched_roi_pct_no": null, "matched_contracts_no": null, "matched_fee_pc_no": null, "matched_dollars_yes": null, "matched_avg_price_yes": null, "matched_roi_pct_yes": null, "matched_contracts_yes": null, "matched_fee_pc_yes": null, "game_start_time": "2026-07-02T00:00:00+00:00", "sharp_action_no": false, "sharp_action_yes": false, "exp_per_player_no": null, "exp_per_player_yes": null}, {"ticker": "KXWCSOA-26JUL01USABIH-BIHEDZEKONA", "side": "no", "price": 60, "remaining_count": 407.0, "created_time": "2026-07-01T23:03:06.840623Z", "game": "USABIH", "team": "BIH", "total": null, "stat_type": "soa", "lastname": "DZEKO", "full_name": "Edin Dzeko", "proj_min": 75.0, "pks": "Yes - 60%", "prob": 76.45, "prob_no": 76.45, "prob_yes": 23.55, "roi_pct": 27.4, "matched_dollars_no": null, "matched_avg_price_no": null, "matched_roi_pct_no": null, "matched_contracts_no": null, "matched_fee_pc_no": null, "matched_dollars_yes": null, "matched_avg_price_yes": null, "matched_roi_pct_yes": null, "matched_contracts_yes": null, "matched_fee_pc_yes": null, "game_start_time": "2026-07-02T00:00:00+00:00", "sharp_action_no": false, "sharp_action_yes": false, "exp_per_player_no": null, "exp_per_player_yes": null}, {"ticker": "KXWCSOA-26JUL01USABIH-BIHADEDIC17", "side": "no", "price": 76, "remaining_count": 492.0, "created_time": "2026-07-01T23:02:59.400616Z", "game": "USABIH", "team": "BIH", "total": null, "stat_type": "soa", "lastname": "DEDIC", "full_name": "Amar Dedic", "proj_min": 80.0, "pks": null, "prob": 90.6, "prob_no": 90.6, "prob_yes": 9.4, "roi_pct": 19.2, "matched_dollars_no": null, "matched_avg_price_no": null, "matched_roi_pct_no": null, "matched_contracts_no": null, "matched_fee_pc_no": null, "matched_dollars_yes": null, "matched_avg_price_yes": null, "matched_roi_pct_yes": null, "matched_contracts_yes": null, "matched_fee_pc_yes": null, "game_start_time": "2026-07-02T00:00:00+00:00", "sharp_action_no": false, "sharp_action_yes": false, "exp_per_player_no": 0.88, "exp_per_player_yes": null}, {"ticker": "KXWCSOA-26JUL01USABIH-USATREAM3", "side": "no", "price": 75, "remaining_count": 304.0, "created_time": "2026-07-01T23:02:56.036349Z", "game": "USABIH", "team": "USA", "total": null, "stat_type": "soa", "lastname": "REAM", "full_name": "Tim Ream", "proj_min": 90.0, "pks": null, "prob": 91.08, "prob_no": 91.08, "prob_yes": 8.92, "roi_pct": 21.4, "matched_dollars_no": null, "matched_avg_price_no": null, "matched_roi_pct_no": null, "matched_contracts_no": null, "matched_fee_pc_no": null, "matched_dollars_yes": null, "matched_avg_price_yes": null, "matched_roi_pct_yes": null, "matched_contracts_yes": null, "matched_fee_pc_yes": null, "game_start_time": "2026-07-02T00:00:00+00:00", "sharp_action_no": false, "sharp_action_yes": false, "exp_per_player_no": null, "exp_per_player_yes": null}, {"ticker": "KXWCSOA-26JUL01USABIH-USACRICHA26", "side": "no", "price": 75, "remaining_count": 459.0, "created_time": "2026-07-01T23:02:52.918859Z", "game": "USABIH", "team": "USA", "total": null, "stat_type": "soa", "lastname": "RICHA", "full_name": "Chris Richards", "proj_min": 90.0, "pks": null, "prob": 91.34, "prob_no": 91.34, "prob_yes": 8.66, "roi_pct": 21.8, "matched_dollars_no": null, "matched_avg_price_no": null, "matched_roi_pct_no": null, "matched_contracts_no": null, "matched_fee_pc_no": null, "matched_dollars_yes": null, "matched_avg_price_yes": null, "matched_roi_pct_yes": null, "matched_contracts_yes": null, "matched_fee_pc_yes": null, "game_start_time": "2026-07-02T00:00:00+00:00", "sharp_action_no": false, "sharp_action_yes": false, "exp_per_player_no": 0.88, "exp_per_player_yes": null}, {"ticker": "KXWCSOA-26JUL01USABIH-BIHAGIGOV8", "side": "no", "price": 81, "remaining_count": 425.0, "created_time": "2026-07-01T23:02:50.767482Z", "game": "USABIH", "team": "BIH", "total": null, "stat_type": "soa", "lastname": "GIGOV", "full_name": "Armin Gigovic", "proj_min": 70.0, "pks": null, "prob": 92.1, "prob_no": 92.1, "prob_yes": 7.9, "roi_pct": 13.7, "matched_dollars_no": null, "matched_avg_price_no": null, "matched_roi_pct_no": null, "matched_contracts_no": null, "matched_fee_pc_no": null, "matched_dollars_yes": null, "matched_avg_price_yes": null, "matched_roi_pct_yes": null, "matched_contracts_yes": null, "matched_fee_pc_yes": null, "game_start_time": "2026-07-02T00:00:00+00:00", "sharp_action_no": false, "sharp_action_yes": false, "exp_per_player_no": 0.88, "exp_per_player_yes": null}, {"ticker": "KXWCSOA-26JUL01USABIH-BIHSKOLAS23", "side": "no", "price": 82, "remaining_count": 306.0, "created_time": "2026-07-01T23:02:46.425027Z", "game": "USABIH", "team": "BIH", "total": null, "stat_type": "soa", "lastname": "KOLAS", "full_name": "Sead Kolasinac", "proj_min": 85.0, "pks": null, "prob": 93.08, "prob_no": 93.08, "prob_yes": 6.92, "roi_pct": 13.5, "matched_dollars_no": null, "matched_avg_price_no": null, "matched_roi_pct_no": null, "matched_contracts_no": null, "matched_fee_pc_no": null, "matched_dollars_yes": null, "matched_avg_price_yes": null, "matched_roi_pct_yes": null, "matched_contracts_yes": null, "matched_fee_pc_yes": null, "game_start_time": "2026-07-02T00:00:00+00:00", "sharp_action_no": false, "sharp_action_yes": false, "exp_per_player_no": 0.88, "exp_per_player_yes": null}, {"ticker": "KXWCSOA-26JUL01USABIH-BIHTMUHAR80", "side": "no", "price": 80, "remaining_count": 433.0, "created_time": "2026-07-01T23:02:42.970157Z", "game": "USABIH", "team": "BIH", "total": null, "stat_type": "soa", "lastname": "MUHAR", "full_name": "Tarik Muharemovic", "proj_min": 90.0, "pks": null, "prob": 95.54, "prob_no": 95.54, "prob_yes": 4.46, "roi_pct": 19.4, "matched_dollars_no": null, "matched_avg_price_no": null, "matched_roi_pct_no": null, "matched_contracts_no": null, "matched_fee_pc_no": null, "matched_dollars_yes": null, "matched_avg_price_yes": null, "matched_roi_pct_yes": null, "matched_contracts_yes": null, "matched_fee_pc_yes": null, "game_start_time": "2026-07-02T00:00:00+00:00", "sharp_action_no": false, "sharp_action_yes": false, "exp_per_player_no": 0.88, "exp_per_player_yes": null}, {"ticker": "KXWCSOA-26JUL01USABIH-BIHNKATIC18", "side": "no", "price": 80, "remaining_count": 483.0, "created_time": "2026-07-01T23:02:40.607778Z", "game": "USABIH", "team": "BIH", "total": null, "stat_type": "soa", "lastname": "KATIC", "full_name": "Nikola Katic", "proj_min": 90.0, "pks": null, "prob": 95.56, "prob_no": 95.56, "prob_yes": 4.44, "roi_pct": 19.5, "matched_dollars_no": null, "matched_avg_price_no": null, "matched_roi_pct_no": null, "matched_contracts_no": null, "matched_fee_pc_no": null, "matched_dollars_yes": null, "matched_avg_price_yes": null, "matched_roi_pct_yes": null, "matched_contracts_yes": null, "matched_fee_pc_yes": null, "game_start_time": "2026-07-02T00:00:00+00:00", "sharp_action_no": false, "sharp_action_yes": false, "exp_per_player_no": 0.88, "exp_per_player_yes": null}, {"ticker": "KXWCSOA-26JUL01USABIH-USATADAMS12", "side": "no", "price": 80, "remaining_count": 477.0, "created_time": "2026-07-01T23:02:38.36653Z", "game": "USABIH", "team": "USA", "total": null, "stat_type": "soa", "lastname": "ADAMS", "full_name": "Tyler Adams", "proj_min": 90.0, "pks": null, "prob": 95.68, "prob_no": 95.68, "prob_yes": 4.32, "roi_pct": 19.6, "matched_dollars_no": null, "matched_avg_price_no": null, "matched_roi_pct_no": null, "matched_contracts_no": null, "matched_fee_pc_no": null, "matched_dollars_yes": null, "matched_avg_price_yes": null, "matched_roi_pct_yes": null, "matched_contracts_yes": null, "matched_fee_pc_yes": null, "game_start_time": "2026-07-02T00:00:00+00:00", "sharp_action_no": false, "sharp_action_yes": false, "exp_per_player_no": 0.88, "exp_per_player_yes": null}, {"ticker": "KXWCSOA-26JUL01USABIH-BIHISUNJI26", "side": "no", "price": 80, "remaining_count": 400.0, "created_time": "2026-07-01T23:02:36.524009Z", "game": "USABIH", "team": "BIH", "total": null, "stat_type": "soa", "lastname": "SUNJI", "full_name": "Ivan Sunjic", "proj_min": 65.0, "pks": null, "prob": 97.52, "prob_no": 97.52, "prob_yes": 2.48, "roi_pct": 21.9, "matched_dollars_no": null, "matched_avg_price_no": null, "matched_roi_pct_no": null, "matched_contracts_no": null, "matched_fee_pc_no": null, "matched_dollars_yes": null, "matched_avg_price_yes": null, "matched_roi_pct_yes": null, "matched_contracts_yes": null, "matched_fee_pc_yes": null, "game_start_time": "2026-07-02T00:00:00+00:00", "sharp_action_no": false, "sharp_action_yes": false, "exp_per_player_no": 0.88, "exp_per_player_yes": null}, {"ticker": "KXWCSOA-26JUL01USABIH-BIHSRADEL6", "side": "no", "price": 80, "remaining_count": 300.0, "created_time": "2026-07-01T23:02:34.331224Z", "game": "USABIH", "team": "BIH", "total": null, "stat_type": "soa", "lastname": "RADEL", "full_name": "Stjepan Radeljic", "proj_min": 80.0, "pks": null, "prob": 98.98, "prob_no": 98.98, "prob_yes": 1.02, "roi_pct": 23.7, "matched_dollars_no": null, "matched_avg_price_no": null, "matched_roi_pct_no": null, "matched_contracts_no": null, "matched_fee_pc_no": null, "matched_dollars_yes": null, "matched_avg_price_yes": null, "matched_roi_pct_yes": null, "matched_contracts_yes": null, "matched_fee_pc_yes": null, "game_start_time": "2026-07-02T00:00:00+00:00", "sharp_action_no": false, "sharp_action_yes": false, "exp_per_player_no": 0.88, "exp_per_player_yes": null}, {"ticker": "KXWCTEAMFIRSTGOAL-26JUL01USABIH-BIH-GOAL", "side": "no", "price": 40, "remaining_count": 369.0, "created_time": "2026-07-01T23:01:01.44832Z", "game": "USABIH", "team": "BIH", "total": null, "stat_type": "teamfirstg", "lastname": "NO GOAL", "full_name": "No Goal", "proj_min": null, "pks": null, "prob": 52.24, "prob_no": 52.24, "prob_yes": 47.76, "roi_pct": 30.6, "matched_dollars_no": null, "matched_avg_price_no": null, "matched_roi_pct_no": null, "matched_contracts_no": null, "matched_fee_pc_no": null, "matched_dollars_yes": null, "matched_avg_price_yes": null, "matched_roi_pct_yes": null, "matched_contracts_yes": null, "matched_fee_pc_yes": null, "game_start_time": "2026-07-02T00:00:00+00:00", "sharp_action_no": false, "sharp_action_yes": false, "exp_per_player_no": null, "exp_per_player_yes": null}, {"ticker": "KXWCTEAMFIRSTGOAL-26JUL01USABIH-USA-CPULIS11", "side": "no", "price": 68, "remaining_count": 364.0, "created_time": "2026-07-01T23:00:52.208245Z", "game": "USABIH", "team": "USA", "total": null, "stat_type": "teamfirstg", "lastname": "PULIS", "full_name": "Christian Pulisic", "proj_min": 90.0, "pks": "Yes - 80%", "prob": 76.36, "prob_no": 76.36, "prob_yes": 23.64, "roi_pct": 12.3, "matched_dollars_no": null, "matched_avg_price_no": null, "matched_roi_pct_no": null, "matched_contracts_no": null, "matched_fee_pc_no": null, "matched_dollars_yes": null, "matched_avg_price_yes": null, "matched_roi_pct_yes": null, "matched_contracts_yes": null, "matched_fee_pc_yes": null, "game_start_time": "2026-07-02T00:00:00+00:00", "sharp_action_no": false, "sharp_action_yes": false, "exp_per_player_no": 4711.94, "exp_per_player_yes": 3520.0}, {"ticker": "KXWCTEAMFIRSTGOAL-26JUL01USABIH-BIH-EDZEKONA", "side": "no", "price": 73, "remaining_count": 443.0, "created_time": "2026-07-01T23:00:46.142886Z", "game": "USABIH", "team": "BIH", "total": null, "stat_type": "teamfirstg", "lastname": "DZEKO", "full_name": "Edin Dzeko", "proj_min": 75.0, "pks": "Yes - 60%", "prob": 83.01, "prob_no": 83.01, "prob_yes": 16.99, "roi_pct": 13.7, "matched_dollars_no": null, "matched_avg_price_no": null, "matched_roi_pct_no": null, "matched_contracts_no": null, "matched_fee_pc_no": null, "matched_dollars_yes": null, "matched_avg_price_yes": null, "matched_roi_pct_yes": null, "matched_contracts_yes": null, "matched_fee_pc_yes": null, "game_start_time": "2026-07-02T00:00:00+00:00", "sharp_action_no": false, "sharp_action_yes": false, "exp_per_player_no": null, "exp_per_player_yes": null}, {"ticker": "KXWCTEAMFIRSTGOAL-26JUL01USABIH-USA-MTILLM10", "side": "no", "price": 80, "remaining_count": 437.0, "created_time": "2026-07-01T23:00:40.010124Z", "game": "USABIH", "team": "USA", "total": null, "stat_type": "teamfirstg", "lastname": "TILLM", "full_name": "Malik Tillman", "proj_min": 85.0, "pks": null, "prob": 91.09, "prob_no": 91.09, "prob_yes": 8.91, "roi_pct": 13.9, "matched_dollars_no": null, "matched_avg_price_no": null, "matched_roi_pct_no": null, "matched_contracts_no": null, "matched_fee_pc_no": null, "matched_dollars_yes": null, "matched_avg_price_yes": null, "matched_roi_pct_yes": null, "matched_contracts_yes": null, "matched_fee_pc_yes": null, "game_start_time": "2026-07-02T00:00:00+00:00", "sharp_action_no": false, "sharp_action_yes": false, "exp_per_player_no": null, "exp_per_player_yes": null}, {"ticker": "KXWCTEAMFIRSTGOAL-26JUL01USABIH-BIH-KALAJB27", "side": "no", "price": 80, "remaining_count": 302.0, "created_time": "2026-07-01T23:00:32.890176Z", "game": "USABIH", "team": "BIH", "total": null, "stat_type": "teamfirstg", "lastname": "ALAJB", "full_name": "Kerim Alajbegovic", "proj_min": 80.0, "pks": "Maybe", "prob": 91.21, "prob_no": 91.21, "prob_yes": 8.79, "roi_pct": 14.0, "matched_dollars_no": null, "matched_avg_price_no": null, "matched_roi_pct_no": null, "matched_contracts_no": null, "matched_fee_pc_no": null, "matched_dollars_yes": null, "matched_avg_price_yes": null, "matched_roi_pct_yes": null, "matched_contracts_yes": null, "matched_fee_pc_yes": null, "game_start_time": "2026-07-02T00:00:00+00:00", "sharp_action_no": false, "sharp_action_yes": false, "exp_per_player_no": 445.0, "exp_per_player_yes": null}, {"ticker": "KXWCTEAMFIRSTGOAL-26JUL01USABIH-USA-SDEST8", "side": "no", "price": 88, "remaining_count": 331.0, "created_time": "2026-07-01T23:00:26.129772Z", "game": "USABIH", "team": "USA", "total": null, "stat_type": "teamfirstg", "lastname": "DEST", "full_name": "Sergino Dest", "proj_min": 70.0, "pks": null, "prob": 94.2, "prob_no": 94.2, "prob_yes": 5.8, "roi_pct": 7.0, "matched_dollars_no": 0.88, "matched_avg_price_no": 88.0, "matched_roi_pct_no": 7.0, "matched_contracts_no": 1.0, "matched_fee_pc_no": 0.74, "matched_dollars_yes": null, "matched_avg_price_yes": null, "matched_roi_pct_yes": null, "matched_contracts_yes": null, "matched_fee_pc_yes": null, "game_start_time": "2026-07-02T00:00:00+00:00", "sharp_action_no": false, "sharp_action_yes": false, "exp_per_player_no": 2797.49, "exp_per_player_yes": null}, {"ticker": "KXWCTEAMFIRSTGOAL-26JUL01USABIH-USA-CRICHA26", "side": "no", "price": 88, "remaining_count": 306.0, "created_time": "2026-07-01T23:00:21.890486Z", "game": "USABIH", "team": "USA", "total": null, "stat_type": "teamfirstg", "lastname": "RICHA", "full_name": "Chris Richards", "proj_min": 90.0, "pks": null, "prob": 97.27, "prob_no": 97.27, "prob_yes": 2.73, "roi_pct": 10.5, "matched_dollars_no": 0.88, "matched_avg_price_no": 88.0, "matched_roi_pct_no": 10.5, "matched_contracts_no": 1.0, "matched_fee_pc_no": 0.74, "matched_dollars_yes": null, "matched_avg_price_yes": null, "matched_roi_pct_yes": null, "matched_contracts_yes": null, "matched_fee_pc_yes": null, "game_start_time": "2026-07-02T00:00:00+00:00", "sharp_action_no": false, "sharp_action_yes": false, "exp_per_player_no": 0.88, "exp_per_player_yes": null}, {"ticker": "KXWCTEAMFIRSTGOAL-26JUL01USABIH-BIH-TMUHAR80", "side": "no", "price": 88, "remaining_count": 437.0, "created_time": "2026-07-01T23:00:16.476937Z", "game": "USABIH", "team": "BIH", "total": null, "stat_type": "teamfirstg", "lastname": "MUHAR", "full_name": "Tarik Muharemovic", "proj_min": 90.0, "pks": null, "prob": 97.33, "prob_no": 97.33, "prob_yes": 2.67, "roi_pct": 10.6, "matched_dollars_no": 0.88, "matched_avg_price_no": 88.0, "matched_roi_pct_no": 10.6, "matched_contracts_no": 1.0, "matched_fee_pc_no": 0.74, "matched_dollars_yes": null, "matched_avg_price_yes": null, "matched_roi_pct_yes": null, "matched_contracts_yes": null, "matched_fee_pc_yes": null, "game_start_time": "2026-07-02T00:00:00+00:00", "sharp_action_no": false, "sharp_action_yes": false, "exp_per_player_no": 0.88, "exp_per_player_yes": null}, {"ticker": "KXWCTEAMFIRSTGOAL-26JUL01USABIH-BIH-AGIGOV8", "side": "no", "price": 88, "remaining_count": 377.0, "created_time": "2026-07-01T23:00:12.31211Z", "game": "USABIH", "team": "BIH", "total": null, "stat_type": "teamfirstg", "lastname": "GIGOV", "full_name": "Armin Gigovic", "proj_min": 70.0, "pks": null, "prob": 97.35, "prob_no": 97.35, "prob_yes": 2.65, "roi_pct": 10.6, "matched_dollars_no": 0.88, "matched_avg_price_no": 88.0, "matched_roi_pct_no": 10.6, "matched_contracts_no": 1.0, "matched_fee_pc_no": 0.74, "matched_dollars_yes": null, "matched_avg_price_yes": null, "matched_roi_pct_yes": null, "matched_contracts_yes": null, "matched_fee_pc_yes": null, "game_start_time": "2026-07-02T00:00:00+00:00", "sharp_action_no": false, "sharp_action_yes": false, "exp_per_player_no": 0.88, "exp_per_player_yes": null}, {"ticker": "KXWCTEAMFIRSTGOAL-26JUL01USABIH-BIH-ADEDIC17", "side": "no", "price": 88, "remaining_count": 327.0, "created_time": "2026-07-01T23:00:08.49153Z", "game": "USABIH", "team": "BIH", "total": null, "stat_type": "teamfirstg", "lastname": "DEDIC", "full_name": "Amar Dedic", "proj_min": 80.0, "pks": null, "prob": 98.66, "prob_no": 98.66, "prob_yes": 1.34, "roi_pct": 12.1, "matched_dollars_no": 0.88, "matched_avg_price_no": 88.0, "matched_roi_pct_no": 12.1, "matched_contracts_no": 1.0, "matched_fee_pc_no": 0.74, "matched_dollars_yes": null, "matched_avg_price_yes": null, "matched_roi_pct_yes": null, "matched_contracts_yes": null, "matched_fee_pc_yes": null, "game_start_time": "2026-07-02T00:00:00+00:00", "sharp_action_no": false, "sharp_action_yes": false, "exp_per_player_no": 0.88, "exp_per_player_yes": null}, {"ticker": "KXWCTEAMFIRSTGOAL-26JUL01USABIH-USA-TADAMS12", "side": "no", "price": 88, "remaining_count": 385.0, "created_time": "2026-07-01T23:00:02.883253Z", "game": "USABIH", "team": "USA", "total": null, "stat_type": "teamfirstg", "lastname": "ADAMS", "full_name": "Tyler Adams", "proj_min": 90.0, "pks": null, "prob": 98.68, "prob_no": 98.68, "prob_yes": 1.32, "roi_pct": 12.1, "matched_dollars_no": 0.88, "matched_avg_price_no": 88.0, "matched_roi_pct_no": 12.1, "matched_contracts_no": 1.0, "matched_fee_pc_no": 0.74, "matched_dollars_yes": null, "matched_avg_price_yes": null, "matched_roi_pct_yes": null, "matched_contracts_yes": null, "matched_fee_pc_yes": null, "game_start_time": "2026-07-02T00:00:00+00:00", "sharp_action_no": false, "sharp_action_yes": false, "exp_per_player_no": 0.88, "exp_per_player_yes": null}, {"ticker": "KXWCTEAMFIRSTGOAL-26JUL01USABIH-BIH-SRADEL6", "side": "no", "price": 88, "remaining_count": 400.0, "created_time": "2026-07-01T22:59:58.86574Z", "game": "USABIH", "team": "BIH", "total": null, "stat_type": "teamfirstg", "lastname": "RADEL", "full_name": "Stjepan Radeljic", "proj_min": 80.0, "pks": null, "prob": 99.67, "prob_no": 99.67, "prob_yes": 0.33, "roi_pct": 13.3, "matched_dollars_no": 0.88, "matched_avg_price_no": 88.0, "matched_roi_pct_no": 13.3, "matched_contracts_no": 1.0, "matched_fee_pc_no": 0.74, "matched_dollars_yes": null, "matched_avg_price_yes": null, "matched_roi_pct_yes": null, "matched_contracts_yes": null, "matched_fee_pc_yes": null, "game_start_time": "2026-07-02T00:00:00+00:00", "sharp_action_no": false, "sharp_action_yes": false, "exp_per_player_no": 0.88, "exp_per_player_yes": null}, {"ticker": "KXWCTEAMFIRSTGOAL-26JUL01USABIH-BIH-SKOLAS23", "side": "no", "price": 88, "remaining_count": 314.0, "created_time": "2026-07-01T22:59:54.226961Z", "game": "USABIH", "team": "BIH", "total": null, "stat_type": "teamfirstg", "lastname": "KOLAS", "full_name": "Sead Kolasinac", "proj_min": 85.0, "pks": null, "prob": 99.67, "prob_no": 99.67, "prob_yes": 0.33, "roi_pct": 13.3, "matched_dollars_no": 0.88, "matched_avg_price_no": 88.0, "matched_roi_pct_no": 13.3, "matched_contracts_no": 1.0, "matched_fee_pc_no": 0.74, "matched_dollars_yes": null, "matched_avg_price_yes": null, "matched_roi_pct_yes": null, "matched_contracts_yes": null, "matched_fee_pc_yes": null, "game_start_time": "2026-07-02T00:00:00+00:00", "sharp_action_no": false, "sharp_action_yes": false, "exp_per_player_no": 0.88, "exp_per_player_yes": null}, {"ticker": "KXWCTEAMFIRSTGOAL-26JUL01USABIH-USA-FBALOG9", "side": "no", "price": 65, "remaining_count": 309.0, "created_time": "2026-07-01T22:59:45.54025Z", "game": "USABIH", "team": "USA", "total": null, "stat_type": "teamfirstg", "lastname": "BALOG", "full_name": "Folarin Balogun", "proj_min": 80.0, "pks": "Maybe - 20%", "prob": 72.22, "prob_no": 72.22, "prob_yes": 27.78, "roi_pct": 11.1, "matched_dollars_no": null, "matched_avg_price_no": null, "matched_roi_pct_no": null, "matched_contracts_no": null, "matched_fee_pc_no": null, "matched_dollars_yes": null, "matched_avg_price_yes": null, "matched_roi_pct_yes": null, "matched_contracts_yes": null, "matched_fee_pc_yes": null, "game_start_time": "2026-07-02T00:00:00+00:00", "sharp_action_no": false, "sharp_action_yes": false, "exp_per_player_no": 1990.74, "exp_per_player_yes": 544.13}, {"ticker": "KXWCTEAMFIRSTGOAL-26JUL01USABIH-USA-GOAL", "side": "no", "price": 80, "remaining_count": 384.0, "created_time": "2026-07-01T22:59:38.543969Z", "game": "USABIH", "team": "USA", "total": null, "stat_type": "teamfirstg", "lastname": "NO GOAL", "full_name": "No Goal", "proj_min": null, "pks": null, "prob": 90.46, "prob_no": 90.46, "prob_yes": 9.54, "roi_pct": 13.1, "matched_dollars_no": null, "matched_avg_price_no": null, "matched_roi_pct_no": null, "matched_contracts_no": null, "matched_fee_pc_no": null, "matched_dollars_yes": null, "matched_avg_price_yes": null, "matched_roi_pct_yes": null, "matched_contracts_yes": null, "matched_fee_pc_yes": null, "game_start_time": "2026-07-02T00:00:00+00:00", "sharp_action_no": false, "sharp_action_yes": false, "exp_per_player_no": null, "exp_per_player_yes": null}, {"ticker": "KXWCTEAMFIRSTGOAL-26JUL01USABIH-BIH-EDEMIR9", "side": "no", "price": 84, "remaining_count": 389.0, "created_time": "2026-07-01T22:59:32.286868Z", "game": "USABIH", "team": "BIH", "total": null, "stat_type": "teamfirstg", "lastname": "DEMIR", "full_name": "Ermedin Demirovic", "proj_min": 85.0, "pks": null, "prob": 91.41, "prob_no": 91.41, "prob_yes": 8.59, "roi_pct": 8.8, "matched_dollars_no": null, "matched_avg_price_no": null, "matched_roi_pct_no": null, "matched_contracts_no": null, "matched_fee_pc_no": null, "matched_dollars_yes": null, "matched_avg_price_yes": null, "matched_roi_pct_yes": null, "matched_contracts_yes": null, "matched_fee_pc_yes": null, "game_start_time": "2026-07-02T00:00:00+00:00", "sharp_action_no": false, "sharp_action_yes": false, "exp_per_player_no": 6.26, "exp_per_player_yes": null}, {"ticker": "KXWCTEAMFIRSTGOAL-26JUL01USABIH-USA-AFREEM3", "side": "no", "price": 85, "remaining_count": 407.54, "created_time": "2026-07-01T22:59:24.322384Z", "game": "USABIH", "team": "USA", "total": null, "stat_type": "teamfirstg", "lastname": "FREEM", "full_name": "Alex Freeman", "proj_min": 85.0, "pks": null, "prob": 93.64, "prob_no": 93.64, "prob_yes": 6.36, "roi_pct": 10.2, "matched_dollars_no": 26.74, "matched_avg_price_no": 85.0, "matched_roi_pct_no": 10.2, "matched_contracts_no": 31.46, "matched_fee_pc_no": 0.0, "matched_dollars_yes": null, "matched_avg_price_yes": null, "matched_roi_pct_yes": null, "matched_contracts_yes": null, "matched_fee_pc_yes": null, "game_start_time": "2026-07-02T00:00:00+00:00", "sharp_action_no": false, "sharp_action_yes": false, "exp_per_player_no": 63.27, "exp_per_player_yes": 3.29}, {"ticker": "KXWCTEAMFIRSTGOAL-26JUL01USABIH-BIH-NKATIC18", "side": "no", "price": 90, "remaining_count": 435.0, "created_time": "2026-07-01T22:59:15.817334Z", "game": "USABIH", "team": "BIH", "total": null, "stat_type": "teamfirstg", "lastname": "KATIC", "full_name": "Nikola Katic", "proj_min": 90.0, "pks": null, "prob": 97.33, "prob_no": 97.33, "prob_yes": 2.67, "roi_pct": 8.1, "matched_dollars_no": 0.88, "matched_avg_price_no": 88.0, "matched_roi_pct_no": 10.6, "matched_contracts_no": 1.0, "matched_fee_pc_no": 0.74, "matched_dollars_yes": null, "matched_avg_price_yes": null, "matched_roi_pct_yes": null, "matched_contracts_yes": null, "matched_fee_pc_yes": null, "game_start_time": "2026-07-02T00:00:00+00:00", "sharp_action_no": false, "sharp_action_yes": false, "exp_per_player_no": 0.88, "exp_per_player_yes": null}, {"ticker": "KXWCTEAMFIRSTGOAL-26JUL01USABIH-USA-AROBIN33", "side": "no", "price": 90, "remaining_count": 468.0, "created_time": "2026-07-01T22:59:05.125792Z", "game": "USABIH", "team": "USA", "total": null, "stat_type": "teamfirstg", "lastname": "ROBIN", "full_name": "Antonee Robinson", "proj_min": 90.0, "pks": null, "prob": 97.31, "prob_no": 97.31, "prob_yes": 2.69, "roi_pct": 8.1, "matched_dollars_no": 0.88, "matched_avg_price_no": 88.0, "matched_roi_pct_no": 10.6, "matched_contracts_no": 1.0, "matched_fee_pc_no": 0.74, "matched_dollars_yes": null, "matched_avg_price_yes": null, "matched_roi_pct_yes": null, "matched_contracts_yes": null, "matched_fee_pc_yes": null, "game_start_time": "2026-07-02T00:00:00+00:00", "sharp_action_no": false, "sharp_action_yes": false, "exp_per_player_no": 0.88, "exp_per_player_yes": 75.82}, {"ticker": "KXWCTEAMFIRSTGOAL-26JUL01USABIH-BIH-ISUNJI26", "side": "no", "price": 90, "remaining_count": 424.0, "created_time": "2026-07-01T22:58:33.424559Z", "game": "USABIH", "team": "BIH", "total": null, "stat_type": "teamfirstg", "lastname": "SUNJI", "full_name": "Ivan Sunjic", "proj_min": 65.0, "pks": null, "prob": 98.85, "prob_no": 98.85, "prob_yes": 1.15, "roi_pct": 9.8, "matched_dollars_no": 0.88, "matched_avg_price_no": 88.0, "matched_roi_pct_no": 12.3, "matched_contracts_no": 1.0, "matched_fee_pc_no": 0.74, "matched_dollars_yes": null, "matched_avg_price_yes": null, "matched_roi_pct_yes": null, "matched_contracts_yes": null, "matched_fee_pc_yes": null, "game_start_time": "2026-07-02T00:00:00+00:00", "sharp_action_no": false, "sharp_action_yes": false, "exp_per_player_no": 0.88, "exp_per_player_yes": null}, {"ticker": "KXWCTEAMFIRSTGOAL-26JUL01USABIH-USA-TREAM3", "side": "no", "price": 82, "remaining_count": 439.0, "created_time": "2026-07-01T22:58:21.247541Z", "game": "USABIH", "team": "USA", "total": null, "stat_type": "teamfirstg", "lastname": "REAM", "full_name": "Tim Ream", "proj_min": 90.0, "pks": null, "prob": 99.1, "prob_no": 99.1, "prob_yes": 0.9, "roi_pct": 20.9, "matched_dollars_no": null, "matched_avg_price_no": null, "matched_roi_pct_no": null, "matched_contracts_no": null, "matched_fee_pc_no": null, "matched_dollars_yes": null, "matched_avg_price_yes": null, "matched_roi_pct_yes": null, "matched_contracts_yes": null, "matched_fee_pc_yes": null, "game_start_time": "2026-07-02T00:00:00+00:00", "sharp_action_no": false, "sharp_action_yes": false, "exp_per_player_no": null, "exp_per_player_yes": null}, {"ticker": "KXWCTEAMFIRSTGOAL-26JUL01USABIH-USA-WMCKEN22", "side": "no", "price": 80, "remaining_count": 498.0, "created_time": "2026-07-01T22:58:19.584657Z", "game": "USABIH", "team": "USA", "total": null, "stat_type": "teamfirstg", "lastname": "MCKEN", "full_name": "Weston McKennie", "proj_min": 90.0, "pks": null, "prob": 93.3, "prob_no": 93.3, "prob_yes": 6.7, "roi_pct": 16.6, "matched_dollars_no": null, "matched_avg_price_no": null, "matched_roi_pct_no": null, "matched_contracts_no": null, "matched_fee_pc_no": null, "matched_dollars_yes": null, "matched_avg_price_yes": null, "matched_roi_pct_yes": null, "matched_contracts_yes": null, "matched_fee_pc_yes": null, "game_start_time": "2026-07-02T00:00:00+00:00", "sharp_action_no": false, "sharp_action_yes": false, "exp_per_player_no": 3257.35, "exp_per_player_yes": 15.74}, {"ticker": "KXWCAST-26JUL01USABIH-USASDEST8-1", "side": "no", "price": 80, "remaining_count": 421.0, "created_time": "2026-07-01T22:57:27.920854Z", "game": "USABIH", "team": "USA", "total": 0.5, "stat_type": "assists", "lastname": "DEST", "full_name": "Sergino Dest", "proj_min": 70.0, "pks": null, "prob": 90.16, "prob_no": 90.16, "prob_yes": 9.84, "roi_pct": 12.7, "matched_dollars_no": 800.0, "matched_avg_price_no": 80.0, "matched_roi_pct_no": 12.7, "matched_contracts_no": 1000.0, "matched_fee_pc_no": 0.0, "matched_dollars_yes": null, "matched_avg_price_yes": null, "matched_roi_pct_yes": null, "matched_contracts_yes": null, "matched_fee_pc_yes": null, "game_start_time": "2026-07-02T00:00:00+00:00", "sharp_action_no": true, "sharp_action_yes": false, "exp_per_player_no": 2797.49, "exp_per_player_yes": null}, {"ticker": "KXWCSOA-26JUL01USABIH-BIHEDEMIR9", "side": "no", "price": 78, "remaining_count": 1000.0, "created_time": "2026-07-01T22:54:48.965732Z", "game": "USABIH", "team": "BIH", "total": null, "stat_type": "soa", "lastname": "DEMIR", "full_name": "Ermedin Demirovic", "proj_min": 85.0, "pks": null, "prob": 85.87, "prob_no": 85.87, "prob_yes": 14.13, "roi_pct": 10.1, "matched_dollars_no": null, "matched_avg_price_no": null, "matched_roi_pct_no": null, "matched_contracts_no": null, "matched_fee_pc_no": null, "matched_dollars_yes": null, "matched_avg_price_yes": null, "matched_roi_pct_yes": null, "matched_contracts_yes": null, "matched_fee_pc_yes": null, "game_start_time": "2026-07-02T00:00:00+00:00", "sharp_action_no": false, "sharp_action_yes": false, "exp_per_player_no": 6.26, "exp_per_player_yes": null}, {"ticker": "KXWCGOAL-26JUL01USABIH-USAAFREEM3-1", "side": "yes", "price": 7, "remaining_count": 372.97, "created_time": "2026-07-01T22:49:36.130295Z", "game": "USABIH", "team": "USA", "total": 0.5, "stat_type": "goals", "lastname": "FREEM", "full_name": "Alex Freeman", "proj_min": 85.0, "pks": null, "prob": 13.63, "prob_no": 86.37, "prob_yes": 13.63, "roi_pct": 94.7, "matched_dollars_no": null, "matched_avg_price_no": null, "matched_roi_pct_no": null, "matched_contracts_no": null, "matched_fee_pc_no": null, "matched_dollars_yes": 3.29, "matched_avg_price_yes": 7.0, "matched_roi_pct_yes": 94.7, "matched_contracts_yes": 47.03, "matched_fee_pc_yes": 0.0, "game_start_time": "2026-07-02T00:00:00+00:00", "sharp_action_no": false, "sharp_action_yes": false, "exp_per_player_no": 63.27, "exp_per_player_yes": 3.29}, {"ticker": "KXWCGOAL-26JUL01USABIH-BIHKALAJB27-1", "side": "yes", "price": 9, "remaining_count": 500.0, "created_time": "2026-07-01T22:49:18.504115Z", "game": "USABIH", "team": "BIH", "total": 0.5, "stat_type": "goals", "lastname": "ALAJB", "full_name": "Kerim Alajbegovic", "proj_min": 80.0, "pks": "Maybe", "prob": 11.13, "prob_no": 88.87, "prob_yes": 11.13, "roi_pct": 23.7, "matched_dollars_no": 445.0, "matched_avg_price_no": 89.0, "matched_roi_pct_no": -0.1, "matched_contracts_no": 500.0, "matched_fee_pc_no": 0.0, "matched_dollars_yes": null, "matched_avg_price_yes": null, "matched_roi_pct_yes": null, "matched_contracts_yes": null, "matched_fee_pc_yes": null, "game_start_time": "2026-07-02T00:00:00+00:00", "sharp_action_no": true, "sharp_action_yes": false, "exp_per_player_no": 445.0, "exp_per_player_yes": null}, {"ticker": "KXWCGOAL-26JUL01USABIH-USACPULIS11-2", "side": "yes", "price": 10, "remaining_count": 800.0, "created_time": "2026-07-01T22:49:03.828764Z", "game": "USABIH", "team": "USA", "total": 1.5, "stat_type": "goals", "lastname": "PULIS", "full_name": "Christian Pulisic", "proj_min": 90.0, "pks": "Yes - 80%", "prob": 11.48, "prob_no": 88.52, "prob_yes": 11.48, "roi_pct": 14.8, "matched_dollars_no": 712.0, "matched_avg_price_no": 89.0, "matched_roi_pct_no": -0.5, "matched_contracts_no": 800.0, "matched_fee_pc_no": 0.0, "matched_dollars_yes": null, "matched_avg_price_yes": null, "matched_roi_pct_yes": null, "matched_contracts_yes": null, "matched_fee_pc_yes": null, "game_start_time": "2026-07-02T00:00:00+00:00", "sharp_action_no": true, "sharp_action_yes": false, "exp_per_player_no": 4711.94, "exp_per_player_yes": 3520.0}, {"ticker": "KXWCGOAL-26JUL01USABIH-USAWMCKEN22-1", "side": "no", "price": 82, "remaining_count": 1000.0, "created_time": "2026-07-01T22:47:35.575942Z", "game": "USABIH", "team": "USA", "total": 0.5, "stat_type": "goals", "lastname": "MCKEN", "full_name": "Weston McKennie", "proj_min": 90.0, "pks": null, "prob": 84.66, "prob_no": 84.66, "prob_yes": 15.34, "roi_pct": 3.2, "matched_dollars_no": null, "matched_avg_price_no": null, "matched_roi_pct_no": null, "matched_contracts_no": null, "matched_fee_pc_no": null, "matched_dollars_yes": null, "matched_avg_price_yes": null, "matched_roi_pct_yes": null, "matched_contracts_yes": null, "matched_fee_pc_yes": null, "game_start_time": "2026-07-02T00:00:00+00:00", "sharp_action_no": false, "sharp_action_yes": false, "exp_per_player_no": 3257.35, "exp_per_player_yes": 15.74}, {"ticker": "KXWCSOA-26JUL01USABIH-USAFBALOG9", "side": "yes", "price": 56, "remaining_count": 700.0, "created_time": "2026-07-01T22:44:04.550653Z", "game": "USABIH", "team": "USA", "total": null, "stat_type": "soa", "lastname": "BALOG", "full_name": "Folarin Balogun", "proj_min": 80.0, "pks": "Maybe - 20%", "prob": 52.46, "prob_no": 47.54, "prob_yes": 52.46, "roi_pct": -6.3, "matched_dollars_no": 1218.08, "matched_avg_price_no": 41.66, "matched_roi_pct_no": 14.1, "matched_contracts_no": 2924.0, "matched_fee_pc_no": 0.0, "matched_dollars_yes": 544.13, "matched_avg_price_yes": 56.0, "matched_roi_pct_yes": -6.3, "matched_contracts_yes": 971.66, "matched_fee_pc_yes": 0.0, "game_start_time": "2026-07-02T00:00:00+00:00", "sharp_action_no": false, "sharp_action_yes": true, "exp_per_player_no": 1990.74, "exp_per_player_yes": 544.13}, {"ticker": "KXWCSOA-26JUL01USABIH-BIHIBASIC13", "side": "no", "price": 89, "remaining_count": 413.0, "created_time": "2026-07-01T22:42:18.083858Z", "game": "USABIH", "team": "BIH", "total": null, "stat_type": "soa", "lastname": "BASIC", "full_name": "Ivan Basic", "proj_min": 25.0, "pks": null, "prob": 96.1, "prob_no": 96.1, "prob_yes": 3.9, "roi_pct": 8.0, "matched_dollars_no": 276.3, "matched_avg_price_no": 90.0, "matched_roi_pct_no": 6.8, "matched_contracts_no": 307.0, "matched_fee_pc_no": 0.0, "matched_dollars_yes": null, "matched_avg_price_yes": null, "matched_roi_pct_yes": null, "matched_contracts_yes": null, "matched_fee_pc_yes": null, "game_start_time": "2026-07-02T00:00:00+00:00", "sharp_action_no": false, "sharp_action_yes": false, "exp_per_player_no": 1867.14, "exp_per_player_yes": null}, {"ticker": "KXWCAST-26JUL01USABIH-BIHIBASIC13-1", "side": "no", "price": 93, "remaining_count": 368.0, "created_time": "2026-07-01T22:40:52.718089Z", "game": "USABIH", "team": "BIH", "total": 0.5, "stat_type": "assists", "lastname": "BASIC", "full_name": "Ivan Basic", "proj_min": 25.0, "pks": null, "prob": 97.61, "prob_no": 97.61, "prob_yes": 2.39, "roi_pct": 5.0, "matched_dollars_no": 713.04, "matched_avg_price_no": 92.6, "matched_roi_pct_no": 5.4, "matched_contracts_no": 770.0, "matched_fee_pc_no": 0.0, "matched_dollars_yes": null, "matched_avg_price_yes": null, "matched_roi_pct_yes": null, "matched_contracts_yes": null, "matched_fee_pc_yes": null, "game_start_time": "2026-07-02T00:00:00+00:00", "sharp_action_no": true, "sharp_action_yes": false, "exp_per_player_no": 1867.14, "exp_per_player_yes": null}, {"ticker": "KXWCSOA-26JUL01USABIH-USACPULIS11", "side": "yes", "price": 58, "remaining_count": 3000.0, "created_time": "2026-07-01T22:09:40.629742Z", "game": "USABIH", "team": "USA", "total": null, "stat_type": "soa", "lastname": "PULIS", "full_name": "Christian Pulisic", "proj_min": 90.0, "pks": "Yes - 80%", "prob": 58.83, "prob_no": 41.17, "prob_yes": 58.83, "roi_pct": 1.4, "matched_dollars_no": 1727.26, "matched_avg_price_no": 38.57, "matched_roi_pct_no": 6.7, "matched_contracts_no": 4478.0, "matched_fee_pc_no": 0.0114, "matched_dollars_yes": 2700.0, "matched_avg_price_yes": 60.0, "matched_roi_pct_yes": -2.0, "matched_contracts_yes": 4500.0, "matched_fee_pc_yes": 0.0, "game_start_time": "2026-07-02T00:00:00+00:00", "sharp_action_no": true, "sharp_action_yes": true, "exp_per_player_no": 4711.94, "exp_per_player_yes": 3520.0}, {"ticker": "KXWCSOA-26JUL01USABIH-USAWMCKEN22", "side": "yes", "price": 36, "remaining_count": 1456.29, "created_time": "2026-07-01T19:55:17.463973Z", "game": "USABIH", "team": "USA", "total": null, "stat_type": "soa", "lastname": "MCKEN", "full_name": "Weston McKennie", "proj_min": 90.0, "pks": null, "prob": 26.13, "prob_no": 73.87, "prob_yes": 26.13, "roi_pct": -27.4, "matched_dollars_no": 998.85, "matched_avg_price_no": 61.24, "matched_roi_pct_no": 20.6, "matched_contracts_no": 1631.0, "matched_fee_pc_no": 0.0, "matched_dollars_yes": 15.74, "matched_avg_price_yes": 36.0, "matched_roi_pct_yes": -27.4, "matched_contracts_yes": 43.71, "matched_fee_pc_yes": 0.0, "game_start_time": "2026-07-02T00:00:00+00:00", "sharp_action_no": false, "sharp_action_yes": false, "exp_per_player_no": 3257.35, "exp_per_player_yes": 15.74}, {"ticker": "KXWCSOA-26JUL01USABIH-USASDEST8", "side": "yes", "price": 22, "remaining_count": 315.0, "created_time": "2026-07-01T19:54:49.989829Z", "game": "USABIH", "team": "USA", "total": null, "stat_type": "soa", "lastname": "DEST", "full_name": "Sergino Dest", "proj_min": 70.0, "pks": null, "prob": 19.55, "prob_no": 80.45, "prob_yes": 19.55, "roi_pct": -11.1, "matched_dollars_no": 873.23, "matched_avg_price_no": 69.91, "matched_roi_pct_no": 15.1, "matched_contracts_no": 1249.0, "matched_fee_pc_no": 0.0312, "matched_dollars_yes": null, "matched_avg_price_yes": null, "matched_roi_pct_yes": null, "matched_contracts_yes": null, "matched_fee_pc_yes": null, "game_start_time": "2026-07-02T00:00:00+00:00", "sharp_action_no": true, "sharp_action_yes": false, "exp_per_player_no": 2797.49, "exp_per_player_yes": null}, {"ticker": "KXWCSOA-26JUL01USABIH-USAFBALOG9", "side": "yes", "price": 56, "remaining_count": 28.34, "created_time": "2026-07-01T19:53:35.30099Z", "game": "USABIH", "team": "USA", "total": null, "stat_type": "soa", "lastname": "BALOG", "full_name": "Folarin Balogun", "proj_min": 80.0, "pks": "Maybe - 20%", "prob": 52.46, "prob_no": 47.54, "prob_yes": 52.46, "roi_pct": -6.3, "matched_dollars_no": 1218.08, "matched_avg_price_no": 41.66, "matched_roi_pct_no": 14.1, "matched_contracts_no": 2924.0, "matched_fee_pc_no": 0.0, "matched_dollars_yes": 544.13, "matched_avg_price_yes": 56.0, "matched_roi_pct_yes": -6.3, "matched_contracts_yes": 971.66, "matched_fee_pc_yes": 0.0, "game_start_time": "2026-07-02T00:00:00+00:00", "sharp_action_no": false, "sharp_action_yes": true, "exp_per_player_no": 1990.74, "exp_per_player_yes": 544.13}, {"ticker": "KXWCAST-26JUL01USABIH-USASDEST8-2", "side": "no", "price": 96, "remaining_count": 415.84, "created_time": "2026-07-01T18:58:09.080422Z", "game": "USABIH", "team": "USA", "total": 1.5, "stat_type": "assists", "lastname": "DEST", "full_name": "Sergino Dest", "proj_min": 70.0, "pks": null, "prob": 99.5, "prob_no": 99.5, "prob_yes": 0.5, "roi_pct": 3.6, "matched_dollars_no": 23.19, "matched_avg_price_no": 96.0, "matched_roi_pct_no": 3.6, "matched_contracts_no": 24.16, "matched_fee_pc_no": 0.0, "matched_dollars_yes": null, "matched_avg_price_yes": null, "matched_roi_pct_yes": null, "matched_contracts_yes": null, "matched_fee_pc_yes": null, "game_start_time": "2026-07-02T00:00:00+00:00", "sharp_action_no": false, "sharp_action_yes": false, "exp_per_player_no": 2797.49, "exp_per_player_yes": null}, {"ticker": "KXWCAST-26JUL01USABIH-BIHEDEMIR9-1", "side": "no", "price": 93, "remaining_count": 500.0, "created_time": "2026-07-01T18:57:56.700157Z", "game": "USABIH", "team": "BIH", "total": 0.5, "stat_type": "assists", "lastname": "DEMIR", "full_name": "Ermedin Demirovic", "proj_min": 85.0, "pks": null, "prob": 96.64, "prob_no": 96.64, "prob_yes": 3.36, "roi_pct": 3.9, "matched_dollars_no": null, "matched_avg_price_no": null, "matched_roi_pct_no": null, "matched_contracts_no": null, "matched_fee_pc_no": null, "matched_dollars_yes": null, "matched_avg_price_yes": null, "matched_roi_pct_yes": null, "matched_contracts_yes": null, "matched_fee_pc_yes": null, "game_start_time": "2026-07-02T00:00:00+00:00", "sharp_action_no": false, "sharp_action_yes": false, "exp_per_player_no": 6.26, "exp_per_player_yes": null}, {"ticker": "KXWCAST-26JUL01USABIH-USAAFREEM3-1", "side": "no", "price": 83, "remaining_count": 358.99, "created_time": "2026-07-01T18:57:40.042637Z", "game": "USABIH", "team": "USA", "total": 0.5, "stat_type": "assists", "lastname": "FREEM", "full_name": "Alex Freeman", "proj_min": 85.0, "pks": null, "prob": 88.76, "prob_no": 88.76, "prob_yes": 11.24, "roi_pct": 6.9, "matched_dollars_no": 36.53, "matched_avg_price_no": 83.0, "matched_roi_pct_no": 6.9, "matched_contracts_no": 44.01, "matched_fee_pc_no": 0.0, "matched_dollars_yes": null, "matched_avg_price_yes": null, "matched_roi_pct_yes": null, "matched_contracts_yes": null, "matched_fee_pc_yes": null, "game_start_time": "2026-07-02T00:00:00+00:00", "sharp_action_no": false, "sharp_action_yes": false, "exp_per_player_no": 63.27, "exp_per_player_yes": 3.29}, {"ticker": "KXWCAST-26JUL01USABIH-BIHAMEMIC99-1", "side": "no", "price": 91, "remaining_count": 327.0, "created_time": "2026-07-01T18:57:22.256776Z", "game": "USABIH", "team": "BIH", "total": 0.5, "stat_type": "assists", "lastname": "MEMIC", "full_name": "Amar Memic", "proj_min": 10.0, "pks": null, "prob": 97.99, "prob_no": 97.99, "prob_yes": 2.01, "roi_pct": 7.7, "matched_dollars_no": null, "matched_avg_price_no": null, "matched_roi_pct_no": null, "matched_contracts_no": null, "matched_fee_pc_no": null, "matched_dollars_yes": null, "matched_avg_price_yes": null, "matched_roi_pct_yes": null, "matched_contracts_yes": null, "matched_fee_pc_yes": null, "game_start_time": "2026-07-02T00:00:00+00:00", "sharp_action_no": false, "sharp_action_yes": false, "exp_per_player_no": 1178.39, "exp_per_player_yes": null}, {"ticker": "KXWCSOA-26JUL01USABIH-BIHAMEMIC99", "side": "no", "price": 85, "remaining_count": 387.0, "created_time": "2026-07-01T18:55:38.553869Z", "game": "USABIH", "team": "BIH", "total": null, "stat_type": "soa", "lastname": "MEMIC", "full_name": "Amar Memic", "proj_min": 10.0, "pks": null, "prob": 96.6, "prob_no": 96.6, "prob_yes": 3.4, "roi_pct": 13.6, "matched_dollars_no": 24.07, "matched_avg_price_no": 83.0, "matched_roi_pct_no": 16.4, "matched_contracts_no": 29.0, "matched_fee_pc_no": 0.0, "matched_dollars_yes": null, "matched_avg_price_yes": null, "matched_roi_pct_yes": null, "matched_contracts_yes": null, "matched_fee_pc_yes": null, "game_start_time": "2026-07-02T00:00:00+00:00", "sharp_action_no": false, "sharp_action_yes": false, "exp_per_player_no": 1178.39, "exp_per_player_yes": null}, {"ticker": "KXWCSOA-26JUL01USABIH-USACPULIS11", "side": "no", "price": 36, "remaining_count": 420.0, "created_time": "2026-07-01T16:56:11.363874Z", "game": "USABIH", "team": "USA", "total": null, "stat_type": "soa", "lastname": "PULIS", "full_name": "Christian Pulisic", "proj_min": 90.0, "pks": "Yes - 80%", "prob": 41.17, "prob_no": 41.17, "prob_yes": 58.83, "roi_pct": 14.4, "matched_dollars_no": 1727.26, "matched_avg_price_no": 38.57, "matched_roi_pct_no": 6.7, "matched_contracts_no": 4478.0, "matched_fee_pc_no": 0.0114, "matched_dollars_yes": 2700.0, "matched_avg_price_yes": 60.0, "matched_roi_pct_yes": -2.0, "matched_contracts_yes": 4500.0, "matched_fee_pc_yes": 0.0, "game_start_time": "2026-07-02T00:00:00+00:00", "sharp_action_no": true, "sharp_action_yes": true, "exp_per_player_no": 4711.94, "exp_per_player_yes": 3520.0}, {"ticker": "KXWCSOA-26JUL01USABIH-BIHAMEMIC99", "side": "no", "price": 83, "remaining_count": 450.0, "created_time": "2026-07-01T16:34:44.897296Z", "game": "USABIH", "team": "BIH", "total": null, "stat_type": "soa", "lastname": "MEMIC", "full_name": "Amar Memic", "proj_min": 10.0, "pks": null, "prob": 96.6, "prob_no": 96.6, "prob_yes": 3.4, "roi_pct": 16.4, "matched_dollars_no": 24.07, "matched_avg_price_no": 83.0, "matched_roi_pct_no": 16.4, "matched_contracts_no": 29.0, "matched_fee_pc_no": 0.0, "matched_dollars_yes": null, "matched_avg_price_yes": null, "matched_roi_pct_yes": null, "matched_contracts_yes": null, "matched_fee_pc_yes": null, "game_start_time": "2026-07-02T00:00:00+00:00", "sharp_action_no": false, "sharp_action_yes": false, "exp_per_player_no": 1178.39, "exp_per_player_yes": null}, {"ticker": "KXWCSOA-26JUL01USABIH-BIHIBASIC13", "side": "no", "price": 87, "remaining_count": 467.0, "created_time": "2026-07-01T11:59:05.187629Z", "game": "USABIH", "team": "BIH", "total": null, "stat_type": "soa", "lastname": "BASIC", "full_name": "Ivan Basic", "proj_min": 25.0, "pks": null, "prob": 96.1, "prob_no": 96.1, "prob_yes": 3.9, "roi_pct": 10.5, "matched_dollars_no": 276.3, "matched_avg_price_no": 90.0, "matched_roi_pct_no": 6.8, "matched_contracts_no": 307.0, "matched_fee_pc_no": 0.0, "matched_dollars_yes": null, "matched_avg_price_yes": null, "matched_roi_pct_yes": null, "matched_contracts_yes": null, "matched_fee_pc_yes": null, "game_start_time": "2026-07-02T00:00:00+00:00", "sharp_action_no": false, "sharp_action_yes": false, "exp_per_player_no": 1867.14, "exp_per_player_yes": null}, {"ticker": "KXWCSOA-26JUL01USABIH-BIHIBASIC13", "side": "no", "price": 88, "remaining_count": 467.0, "created_time": "2026-07-01T11:59:02.602152Z", "game": "USABIH", "team": "BIH", "total": null, "stat_type": "soa", "lastname": "BASIC", "full_name": "Ivan Basic", "proj_min": 25.0, "pks": null, "prob": 96.1, "prob_no": 96.1, "prob_yes": 3.9, "roi_pct": 9.2, "matched_dollars_no": 276.3, "matched_avg_price_no": 90.0, "matched_roi_pct_no": 6.8, "matched_contracts_no": 307.0, "matched_fee_pc_no": 0.0, "matched_dollars_yes": null, "matched_avg_price_yes": null, "matched_roi_pct_yes": null, "matched_contracts_yes": null, "matched_fee_pc_yes": null, "game_start_time": "2026-07-02T00:00:00+00:00", "sharp_action_no": false, "sharp_action_yes": false, "exp_per_player_no": 1867.14, "exp_per_player_yes": null}, {"ticker": "KXWCGOAL-26JUL01USABIH-BIHEDEMIR9-1", "side": "no", "price": 87, "remaining_count": 468.8, "created_time": "2026-07-01T11:56:39.625434Z", "game": "USABIH", "team": "BIH", "total": 0.5, "stat_type": "goals", "lastname": "DEMIR", "full_name": "Ermedin Demirovic", "proj_min": 85.0, "pks": null, "prob": 88.85, "prob_no": 88.85, "prob_yes": 11.15, "roi_pct": 2.1, "matched_dollars_no": 6.26, "matched_avg_price_no": 87.0, "matched_roi_pct_no": 2.1, "matched_contracts_no": 7.2, "matched_fee_pc_no": 0.0, "matched_dollars_yes": null, "matched_avg_price_yes": null, "matched_roi_pct_yes": null, "matched_contracts_yes": null, "matched_fee_pc_yes": null, "game_start_time": "2026-07-02T00:00:00+00:00", "sharp_action_no": false, "sharp_action_yes": false, "exp_per_player_no": 6.26, "exp_per_player_yes": null}, {"ticker": "KXWCAST-26JUL01USABIH-USAAROBIN33-1", "side": "yes", "price": 13, "remaining_count": 175.85, "created_time": "2026-07-01T11:48:46.052338Z", "game": "USABIH", "team": "USA", "total": 0.5, "stat_type": "assists", "lastname": "ROBIN", "full_name": "Antonee Robinson", "proj_min": 90.0, "pks": null, "prob": 21.85, "prob_no": 78.15, "prob_yes": 21.85, "roi_pct": 68.1, "matched_dollars_no": null, "matched_avg_price_no": null, "matched_roi_pct_no": null, "matched_contracts_no": null, "matched_fee_pc_no": null, "matched_dollars_yes": 75.82, "matched_avg_price_yes": 14.17, "matched_roi_pct_yes": 54.2, "matched_contracts_yes": 535.15, "matched_fee_pc_yes": 0.6672, "game_start_time": "2026-07-02T00:00:00+00:00", "sharp_action_no": false, "sharp_action_yes": false, "exp_per_player_no": 0.88, "exp_per_player_yes": 75.82}, {"ticker": "KXWCGOAL-26JUL01USABIH-USACPULIS11-1", "side": "yes", "price": null, "remaining_count": 0, "created_time": "", "game": "USABIH", "team": "USA", "total": 0.5, "stat_type": "goals", "lastname": "PULIS", "full_name": "Christian Pulisic", "proj_min": 90.0, "pks": "Yes - 80%", "prob": 44.8, "prob_no": 55.2, "prob_yes": 44.8, "roi_pct": null, "matched_dollars_no": null, "matched_avg_price_no": null, "matched_roi_pct_no": null, "matched_contracts_no": null, "matched_fee_pc_no": null, "matched_dollars_yes": 820.0, "matched_avg_price_yes": 41.0, "matched_roi_pct_yes": 9.3, "matched_contracts_yes": 2000.0, "matched_fee_pc_yes": 0.0, "game_start_time": "2026-07-02T00:00:00+00:00", "sharp_action_no": false, "sharp_action_yes": true, "exp_per_player_no": 4711.94, "exp_per_player_yes": 3520.0}, {"ticker": "KXWCAST-26JUL01USABIH-USAFBALOG9-1", "side": "no", "price": null, "remaining_count": 0, "created_time": "", "game": "USABIH", "team": "USA", "total": 0.5, "stat_type": "assists", "lastname": "BALOG", "full_name": "Folarin Balogun", "proj_min": 80.0, "pks": "Maybe - 20%", "prob": 86.73, "prob_no": 86.73, "prob_yes": 13.27, "roi_pct": null, "matched_dollars_no": 772.66, "matched_avg_price_no": 80.49, "matched_roi_pct_no": 7.8, "matched_contracts_no": 960.0, "matched_fee_pc_no": 0.0, "matched_dollars_yes": null, "matched_avg_price_yes": null, "matched_roi_pct_yes": null, "matched_contracts_yes": null, "matched_fee_pc_yes": null, "game_start_time": "2026-07-02T00:00:00+00:00", "sharp_action_no": true, "sharp_action_yes": false, "exp_per_player_no": 1990.74, "exp_per_player_yes": 544.13}, {"ticker": "KXWCAST-26JUL01USABIH-USAWMCKEN22-1", "side": "no", "price": null, "remaining_count": 0, "created_time": "", "game": "USABIH", "team": "USA", "total": 0.5, "stat_type": "assists", "lastname": "MCKEN", "full_name": "Weston McKennie", "proj_min": 90.0, "pks": null, "prob": 87.32, "prob_no": 87.32, "prob_yes": 12.68, "roi_pct": null, "matched_dollars_no": 1108.5, "matched_avg_price_no": 76.66, "matched_roi_pct_no": 13.9, "matched_contracts_no": 1446.0, "matched_fee_pc_no": 0.0, "matched_dollars_yes": null, "matched_avg_price_yes": null, "matched_roi_pct_yes": null, "matched_contracts_yes": null, "matched_fee_pc_yes": null, "game_start_time": "2026-07-02T00:00:00+00:00", "sharp_action_no": false, "sharp_action_yes": false, "exp_per_player_no": 3257.35, "exp_per_player_yes": 15.74}, {"ticker": "KXWCAST-26JUL01USABIH-USAWMCKEN22-2", "side": "no", "price": null, "remaining_count": 0, "created_time": "", "game": "USABIH", "team": "USA", "total": 1.5, "stat_type": "assists", "lastname": "MCKEN", "full_name": "Weston McKennie", "proj_min": 90.0, "pks": null, "prob": 99.19, "prob_no": 99.19, "prob_yes": 0.81, "roi_pct": null, "matched_dollars_no": 665.0, "matched_avg_price_no": 95.0, "matched_roi_pct_no": 4.4, "matched_contracts_no": 700.0, "matched_fee_pc_no": 0.0, "matched_dollars_yes": null, "matched_avg_price_yes": null, "matched_roi_pct_yes": null, "matched_contracts_yes": null, "matched_fee_pc_yes": null, "game_start_time": "2026-07-02T00:00:00+00:00", "sharp_action_no": true, "sharp_action_yes": false, "exp_per_player_no": 3257.35, "exp_per_player_yes": 15.74}, {"ticker": "KXWCGOAL-26JUL01USABIH-BIHAMEMIC99-1", "side": "no", "price": null, "remaining_count": 0, "created_time": "", "game": "USABIH", "team": "BIH", "total": 0.5, "stat_type": "goals", "lastname": "MEMIC", "full_name": "Amar Memic", "proj_min": 10.0, "pks": null, "prob": 98.57, "prob_no": 98.57, "prob_yes": 1.43, "roi_pct": null, "matched_dollars_no": 1154.32, "matched_avg_price_no": 94.0, "matched_roi_pct_no": 4.9, "matched_contracts_no": 1228.0, "matched_fee_pc_no": 0.0, "matched_dollars_yes": null, "matched_avg_price_yes": null, "matched_roi_pct_yes": null, "matched_contracts_yes": null, "matched_fee_pc_yes": null, "game_start_time": "2026-07-02T00:00:00+00:00", "sharp_action_no": true, "sharp_action_yes": false, "exp_per_player_no": 1178.39, "exp_per_player_yes": null}, {"ticker": "KXWCAST-26JUL01USABIH-USACPULIS11-2", "side": "no", "price": null, "remaining_count": 0, "created_time": "", "game": "USABIH", "team": "USA", "total": 1.5, "stat_type": "assists", "lastname": "PULIS", "full_name": "Christian Pulisic", "proj_min": 90.0, "pks": "Yes - 80%", "prob": 96.77, "prob_no": 96.77, "prob_yes": 3.23, "roi_pct": null, "matched_dollars_no": 658.0, "matched_avg_price_no": 94.0, "matched_roi_pct_no": 2.9, "matched_contracts_no": 700.0, "matched_fee_pc_no": 0.0119, "matched_dollars_yes": null, "matched_avg_price_yes": null, "matched_roi_pct_yes": null, "matched_contracts_yes": null, "matched_fee_pc_yes": null, "game_start_time": "2026-07-02T00:00:00+00:00", "sharp_action_no": true, "sharp_action_yes": false, "exp_per_player_no": 4711.94, "exp_per_player_yes": 3520.0}, {"ticker": "KXWCGOAL-26JUL01USABIH-BIHIBASIC13-1", "side": "no", "price": null, "remaining_count": 0, "created_time": "", "game": "USABIH", "team": "BIH", "total": 0.5, "stat_type": "goals", "lastname": "BASIC", "full_name": "Ivan Basic", "proj_min": 25.0, "pks": null, "prob": 98.45, "prob_no": 98.45, "prob_yes": 1.55, "roi_pct": null, "matched_dollars_no": 877.8, "matched_avg_price_no": 95.0, "matched_roi_pct_no": 3.6, "matched_contracts_no": 924.0, "matched_fee_pc_no": 0.0, "matched_dollars_yes": null, "matched_avg_price_yes": null, "matched_roi_pct_yes": null, "matched_contracts_yes": null, "matched_fee_pc_yes": null, "game_start_time": "2026-07-02T00:00:00+00:00", "sharp_action_no": false, "sharp_action_yes": false, "exp_per_player_no": 1867.14, "exp_per_player_yes": null}, {"ticker": "KXWCGOAL-26JUL01USABIH-USASDEST8-1", "side": "no", "price": null, "remaining_count": 0, "created_time": "", "game": "USABIH", "team": "USA", "total": 0.5, "stat_type": "goals", "lastname": "DEST", "full_name": "Sergino Dest", "proj_min": 70.0, "pks": null, "prob": 89.24, "prob_no": 89.24, "prob_yes": 10.76, "roi_pct": null, "matched_dollars_no": 1100.19, "matched_avg_price_no": 84.74, "matched_roi_pct_no": 5.3, "matched_contracts_no": 1298.27, "matched_fee_pc_no": 0.0021, "matched_dollars_yes": null, "matched_avg_price_yes": null, "matched_roi_pct_yes": null, "matched_contracts_yes": null, "matched_fee_pc_yes": null, "game_start_time": "2026-07-02T00:00:00+00:00", "sharp_action_no": true, "sharp_action_yes": false, "exp_per_player_no": 2797.49, "exp_per_player_yes": null}, {"ticker": "KXWCAST-26JUL01USABIH-USACPULIS11-1", "side": "no", "price": null, "remaining_count": 0, "created_time": "", "game": "USABIH", "team": "USA", "total": 0.5, "stat_type": "assists", "lastname": "PULIS", "full_name": "Christian Pulisic", "proj_min": 90.0, "pks": "Yes - 80%", "prob": 75.21, "prob_no": 75.21, "prob_yes": 24.79, "roi_pct": null, "matched_dollars_no": 1614.68, "matched_avg_price_no": 71.19, "matched_roi_pct_no": 5.6, "matched_contracts_no": 2268.0, "matched_fee_pc_no": 0.0, "matched_dollars_yes": null, "matched_avg_price_yes": null, "matched_roi_pct_yes": null, "matched_contracts_yes": null, "matched_fee_pc_yes": null, "game_start_time": "2026-07-02T00:00:00+00:00", "sharp_action_no": true, "sharp_action_yes": false, "exp_per_player_no": 4711.94, "exp_per_player_yes": 3520.0}, {"ticker": "KXWCGOAL-26JUL01USABIH-USAWMCKEN22-2", "side": "no", "price": null, "remaining_count": 0, "created_time": "", "game": "USABIH", "team": "USA", "total": 1.5, "stat_type": "goals", "lastname": "MCKEN", "full_name": "Weston McKennie", "proj_min": 90.0, "pks": null, "prob": 98.82, "prob_no": 98.82, "prob_yes": 1.18, "roi_pct": null, "matched_dollars_no": 485.0, "matched_avg_price_no": 97.0, "matched_roi_pct_no": 1.9, "matched_contracts_no": 500.0, "matched_fee_pc_no": 0.0, "matched_dollars_yes": null, "matched_avg_price_yes": null, "matched_roi_pct_yes": null, "matched_contracts_yes": null, "matched_fee_pc_yes": null, "game_start_time": "2026-07-02T00:00:00+00:00", "sharp_action_no": false, "sharp_action_yes": false, "exp_per_player_no": 3257.35, "exp_per_player_yes": 15.74}], "fills": [{"market_ticker": "KXWCGOAL-26JUL01USABIH-USACPULIS11-1", "side": "yes", "price": 41, "contracts": 789.77, "created_time": "2026-07-01T23:02:55+00:00", "created_ms": 1782946975722, "is_taker": false, "fee_cost": "0.000000", "player": "PULIS", "team": "USA", "stat": "goals", "line": 0.5}, {"market_ticker": "KXWCGOAL-26JUL01USABIH-USACPULIS11-1", "side": "yes", "price": 41, "contracts": 20.59, "created_time": "2026-07-01T23:01:22+00:00", "created_ms": 1782946882161, "is_taker": false, "fee_cost": "0.000000", "player": "PULIS", "team": "USA", "stat": "goals", "line": 0.5}, {"market_ticker": "KXWCTEAMFIRSTGOAL-26JUL01USABIH-USA-AFREEM3", "side": "no", "price": 85, "contracts": 31.46, "created_time": "2026-07-01T23:00:59+00:00", "created_ms": 1782946859643, "is_taker": false, "fee_cost": "0.000000", "player": "FREEM", "team": "USA", "stat": "teamfirstg", "line": null}, {"market_ticker": "KXWCTEAMFIRSTGOAL-26JUL01USABIH-USA-SDEST8", "side": "no", "price": 88, "contracts": 1.0, "created_time": "2026-07-01T23:00:26+00:00", "created_ms": 1782946826129, "is_taker": true, "fee_cost": "0.007400", "player": "DEST", "team": "USA", "stat": "teamfirstg", "line": null}, {"market_ticker": "KXWCTEAMFIRSTGOAL-26JUL01USABIH-USA-CRICHA26", "side": "no", "price": 88, "contracts": 1.0, "created_time": "2026-07-01T23:00:21+00:00", "created_ms": 1782946821890, "is_taker": true, "fee_cost": "0.007400", "player": "RICHA", "team": "USA", "stat": "teamfirstg", "line": null}, {"market_ticker": "KXWCTEAMFIRSTGOAL-26JUL01USABIH-BIH-TMUHAR80", "side": "no", "price": 88, "contracts": 1.0, "created_time": "2026-07-01T23:00:16+00:00", "created_ms": 1782946816476, "is_taker": true, "fee_cost": "0.007400", "player": "MUHAR", "team": "BIH", "stat": "teamfirstg", "line": null}, {"market_ticker": "KXWCGOAL-26JUL01USABIH-USACPULIS11-1", "side": "yes", "price": 41, "contracts": 16.47, "created_time": "2026-07-01T23:00:12+00:00", "created_ms": 1782946812811, "is_taker": false, "fee_cost": "0.000000", "player": "PULIS", "team": "USA", "stat": "goals", "line": 0.5}, {"market_ticker": "KXWCTEAMFIRSTGOAL-26JUL01USABIH-BIH-AGIGOV8", "side": "no", "price": 88, "contracts": 1.0, "created_time": "2026-07-01T23:00:12+00:00", "created_ms": 1782946812312, "is_taker": true, "fee_cost": "0.007400", "player": "GIGOV", "team": "BIH", "stat": "teamfirstg", "line": null}, {"market_ticker": "KXWCTEAMFIRSTGOAL-26JUL01USABIH-BIH-ADEDIC17", "side": "no", "price": 88, "contracts": 1.0, "created_time": "2026-07-01T23:00:08+00:00", "created_ms": 1782946808491, "is_taker": true, "fee_cost": "0.007400", "player": "DEDIC", "team": "BIH", "stat": "teamfirstg", "line": null}, {"market_ticker": "KXWCTEAMFIRSTGOAL-26JUL01USABIH-USA-TADAMS12", "side": "no", "price": 88, "contracts": 1.0, "created_time": "2026-07-01T23:00:02+00:00", "created_ms": 1782946802883, "is_taker": true, "fee_cost": "0.007400", "player": "ADAMS", "team": "USA", "stat": "teamfirstg", "line": null}, {"market_ticker": "KXWCTEAMFIRSTGOAL-26JUL01USABIH-BIH-SRADEL6", "side": "no", "price": 88, "contracts": 1.0, "created_time": "2026-07-01T22:59:58+00:00", "created_ms": 1782946798865, "is_taker": true, "fee_cost": "0.007400", "player": "RADEL", "team": "BIH", "stat": "teamfirstg", "line": null}, {"market_ticker": "KXWCTEAMFIRSTGOAL-26JUL01USABIH-BIH-SKOLAS23", "side": "no", "price": 88, "contracts": 1.0, "created_time": "2026-07-01T22:59:54+00:00", "created_ms": 1782946794226, "is_taker": true, "fee_cost": "0.007400", "player": "KOLAS", "team": "BIH", "stat": "teamfirstg", "line": null}, {"market_ticker": "KXWCGOAL-26JUL01USABIH-USACPULIS11-1", "side": "yes", "price": 41, "contracts": 98.85, "created_time": "2026-07-01T22:59:19+00:00", "created_ms": 1782946759482, "is_taker": false, "fee_cost": "0.000000", "player": "PULIS", "team": "USA", "stat": "goals", "line": 0.5}, {"market_ticker": "KXWCTEAMFIRSTGOAL-26JUL01USABIH-BIH-NKATIC18", "side": "no", "price": 88, "contracts": 1.0, "created_time": "2026-07-01T22:59:15+00:00", "created_ms": 1782946755817, "is_taker": true, "fee_cost": "0.007400", "player": "KATIC", "team": "BIH", "stat": "teamfirstg", "line": null}, {"market_ticker": "KXWCAST-26JUL01USABIH-USAFBALOG9-1", "side": "no", "price": 80, "contracts": 494.0, "created_time": "2026-07-01T22:59:11+00:00", "created_ms": 1782946751676, "is_taker": false, "fee_cost": "0.000000", "player": "BALOG", "team": "USA", "stat": "assists", "line": 0.5}, {"market_ticker": "KXWCTEAMFIRSTGOAL-26JUL01USABIH-USA-AROBIN33", "side": "no", "price": 88, "contracts": 1.0, "created_time": "2026-07-01T22:59:05+00:00", "created_ms": 1782946745125, "is_taker": true, "fee_cost": "0.007400", "player": "ROBIN", "team": "USA", "stat": "teamfirstg", "line": null}, {"market_ticker": "KXWCGOAL-26JUL01USABIH-USACPULIS11-1", "side": "yes", "price": 41, "contracts": 45.76, "created_time": "2026-07-01T22:59:04+00:00", "created_ms": 1782946744074, "is_taker": false, "fee_cost": "0.000000", "player": "PULIS", "team": "USA", "stat": "goals", "line": 0.5}, {"market_ticker": "KXWCAST-26JUL01USABIH-USAAFREEM3-1", "side": "no", "price": 83, "contracts": 44.01, "created_time": "2026-07-01T22:58:50+00:00", "created_ms": 1782946730169, "is_taker": false, "fee_cost": "0.000000", "player": "FREEM", "team": "USA", "stat": "assists", "line": 0.5}, {"market_ticker": "KXWCTEAMFIRSTGOAL-26JUL01USABIH-BIH-ISUNJI26", "side": "no", "price": 88, "contracts": 1.0, "created_time": "2026-07-01T22:58:33+00:00", "created_ms": 1782946713424, "is_taker": true, "fee_cost": "0.007400", "player": "SUNJI", "team": "BIH", "stat": "teamfirstg", "line": null}, {"market_ticker": "KXWCGOAL-26JUL01USABIH-USACPULIS11-1", "side": "yes", "price": 41, "contracts": 16.01, "created_time": "2026-07-01T22:57:44+00:00", "created_ms": 1782946664512, "is_taker": false, "fee_cost": "0.000000", "player": "PULIS", "team": "USA", "stat": "goals", "line": 0.5}, {"market_ticker": "KXWCGOAL-26JUL01USABIH-USAAFREEM3-1", "side": "yes", "price": 7, "contracts": 47.03, "created_time": "2026-07-01T22:57:35+00:00", "created_ms": 1782946655081, "is_taker": false, "fee_cost": "0.000000", "player": "FREEM", "team": "USA", "stat": "goals", "line": 0.5}, {"market_ticker": "KXWCGOAL-26JUL01USABIH-USACPULIS11-1", "side": "yes", "price": 41, "contracts": 411.9, "created_time": "2026-07-01T22:57:32+00:00", "created_ms": 1782946652758, "is_taker": false, "fee_cost": "0.000000", "player": "PULIS", "team": "USA", "stat": "goals", "line": 0.5}, {"market_ticker": "KXWCAST-26JUL01USABIH-USAWMCKEN22-1", "side": "no", "price": 76, "contracts": 196.37, "created_time": "2026-07-01T22:57:29+00:00", "created_ms": 1782946649942, "is_taker": false, "fee_cost": "0.000000", "player": "MCKEN", "team": "USA", "stat": "assists", "line": 0.5}, {"market_ticker": "KXWCGOAL-26JUL01USABIH-USACPULIS11-1", "side": "yes", "price": 41, "contracts": 23.99, "created_time": "2026-07-01T22:57:27+00:00", "created_ms": 1782946647509, "is_taker": false, "fee_cost": "0.000000", "player": "PULIS", "team": "USA", "stat": "goals", "line": 0.5}, {"market_ticker": "KXWCGOAL-26JUL01USABIH-USACPULIS11-1", "side": "yes", "price": 41, "contracts": 576.66, "created_time": "2026-07-01T22:57:18+00:00", "created_ms": 1782946638308, "is_taker": false, "fee_cost": "0.000000", "player": "PULIS", "team": "USA", "stat": "goals", "line": 0.5}, {"market_ticker": "KXWCAST-26JUL01USABIH-USAWMCKEN22-1", "side": "no", "price": 76, "contracts": 98.9, "created_time": "2026-07-01T22:57:15+00:00", "created_ms": 1782946635931, "is_taker": false, "fee_cost": "0.000000", "player": "MCKEN", "team": "USA", "stat": "assists", "line": 0.5}, {"market_ticker": "KXWCAST-26JUL01USABIH-USASDEST8-1", "side": "no", "price": 80, "contracts": 434.93, "created_time": "2026-07-01T22:56:47+00:00", "created_ms": 1782946607071, "is_taker": false, "fee_cost": "0.000000", "player": "DEST", "team": "USA", "stat": "assists", "line": 0.5}, {"market_ticker": "KXWCAST-26JUL01USABIH-USAWMCKEN22-1", "side": "no", "price": 76, "contracts": 135.0, "created_time": "2026-07-01T22:56:18+00:00", "created_ms": 1782946578272, "is_taker": false, "fee_cost": "0.000000", "player": "MCKEN", "team": "USA", "stat": "assists", "line": 0.5}, {"market_ticker": "KXWCAST-26JUL01USABIH-USAWMCKEN22-2", "side": "no", "price": 95, "contracts": 79.24, "created_time": "2026-07-01T22:56:17+00:00", "created_ms": 1782946577318, "is_taker": false, "fee_cost": "0.000000", "player": "MCKEN", "team": "USA", "stat": "assists", "line": 1.5}, {"market_ticker": "KXWCAST-26JUL01USABIH-USAWMCKEN22-1", "side": "no", "price": 76, "contracts": 19.78, "created_time": "2026-07-01T22:56:10+00:00", "created_ms": 1782946570385, "is_taker": false, "fee_cost": "0.000000", "player": "MCKEN", "team": "USA", "stat": "assists", "line": 0.5}, {"market_ticker": "KXWCAST-26JUL01USABIH-USAWMCKEN22-1", "side": "no", "price": 76, "contracts": 3.95, "created_time": "2026-07-01T22:55:40+00:00", "created_ms": 1782946540240, "is_taker": false, "fee_cost": "0.000000", "player": "MCKEN", "team": "USA", "stat": "assists", "line": 0.5}, {"market_ticker": "KXWCAST-26JUL01USABIH-USASDEST8-1", "side": "no", "price": 80, "contracts": 99.79, "created_time": "2026-07-01T22:55:36+00:00", "created_ms": 1782946536390, "is_taker": false, "fee_cost": "0.000000", "player": "DEST", "team": "USA", "stat": "assists", "line": 0.5}, {"market_ticker": "KXWCAST-26JUL01USABIH-USAWMCKEN22-1", "side": "no", "price": 76, "contracts": 38.0, "created_time": "2026-07-01T22:55:16+00:00", "created_ms": 1782946516754, "is_taker": false, "fee_cost": "0.000000", "player": "MCKEN", "team": "USA", "stat": "assists", "line": 0.5}, {"market_ticker": "KXWCGOAL-26JUL01USABIH-BIHAMEMIC99-1", "side": "no", "price": 94, "contracts": 37.81, "created_time": "2026-07-01T22:54:56+00:00", "created_ms": 1782946496335, "is_taker": false, "fee_cost": "0.000000", "player": "MEMIC", "team": "BIH", "stat": "goals", "line": 0.5}, {"market_ticker": "KXWCGOAL-26JUL01USABIH-BIHAMEMIC99-1", "side": "no", "price": 94, "contracts": 15.5, "created_time": "2026-07-01T22:54:39+00:00", "created_ms": 1782946479420, "is_taker": false, "fee_cost": "0.000000", "player": "MEMIC", "team": "BIH", "stat": "goals", "line": 0.5}, {"market_ticker": "KXWCAST-26JUL01USABIH-USAWMCKEN22-2", "side": "no", "price": 95, "contracts": 93.76, "created_time": "2026-07-01T22:54:36+00:00", "created_ms": 1782946476860, "is_taker": false, "fee_cost": "0.000000", "player": "MCKEN", "team": "USA", "stat": "assists", "line": 1.5}, {"market_ticker": "KXWCGOAL-26JUL01USABIH-BIHAMEMIC99-1", "side": "no", "price": 94, "contracts": 41.0, "created_time": "2026-07-01T22:54:09+00:00", "created_ms": 1782946449005, "is_taker": false, "fee_cost": "0.000000", "player": "MEMIC", "team": "BIH", "stat": "goals", "line": 0.5}, {"market_ticker": "KXWCGOAL-26JUL01USABIH-BIHAMEMIC99-1", "side": "no", "price": 94, "contracts": 156.37, "created_time": "2026-07-01T22:53:26+00:00", "created_ms": 1782946406825, "is_taker": false, "fee_cost": "0.000000", "player": "MEMIC", "team": "BIH", "stat": "goals", "line": 0.5}, {"market_ticker": "KXWCAST-26JUL01USABIH-USACPULIS11-2", "side": "no", "price": 94, "contracts": 11.58, "created_time": "2026-07-01T22:53:12+00:00", "created_ms": 1782946392081, "is_taker": false, "fee_cost": "0.000000", "player": "PULIS", "team": "USA", "stat": "assists", "line": 1.5}, {"market_ticker": "KXWCGOAL-26JUL01USABIH-BIHAMEMIC99-1", "side": "no", "price": 94, "contracts": 10.0, "created_time": "2026-07-01T22:52:43+00:00", "created_ms": 1782946363737, "is_taker": false, "fee_cost": "0.000000", "player": "MEMIC", "team": "BIH", "stat": "goals", "line": 0.5}, {"market_ticker": "KXWCGOAL-26JUL01USABIH-BIHAMEMIC99-1", "side": "no", "price": 94, "contracts": 78.18, "created_time": "2026-07-01T22:52:42+00:00", "created_ms": 1782946362673, "is_taker": false, "fee_cost": "0.000000", "player": "MEMIC", "team": "BIH", "stat": "goals", "line": 0.5}, {"market_ticker": "KXWCGOAL-26JUL01USABIH-BIHIBASIC13-1", "side": "no", "price": 95, "contracts": 70.33, "created_time": "2026-07-01T22:52:27+00:00", "created_ms": 1782946347806, "is_taker": false, "fee_cost": "0.000000", "player": "BASIC", "team": "BIH", "stat": "goals", "line": 0.5}, {"market_ticker": "KXWCAST-26JUL01USABIH-USACPULIS11-2", "side": "no", "price": 94, "contracts": 292.42, "created_time": "2026-07-01T22:52:19+00:00", "created_ms": 1782946339670, "is_taker": false, "fee_cost": "0.000000", "player": "PULIS", "team": "USA", "stat": "assists", "line": 1.5}, {"market_ticker": "KXWCAST-26JUL01USABIH-USACPULIS11-2", "side": "no", "price": 94, "contracts": 375.0, "created_time": "2026-07-01T22:52:19+00:00", "created_ms": 1782946339204, "is_taker": false, "fee_cost": "0.000000", "player": "PULIS", "team": "USA", "stat": "assists", "line": 1.5}, {"market_ticker": "KXWCGOAL-26JUL01USABIH-BIHAMEMIC99-1", "side": "no", "price": 94, "contracts": 20.0, "created_time": "2026-07-01T22:52:01+00:00", "created_ms": 1782946321268, "is_taker": false, "fee_cost": "0.000000", "player": "MEMIC", "team": "BIH", "stat": "goals", "line": 0.5}, {"market_ticker": "KXWCAST-26JUL01USABIH-USACPULIS11-2", "side": "no", "price": 94, "contracts": 21.0, "created_time": "2026-07-01T22:51:53+00:00", "created_ms": 1782946313467, "is_taker": true, "fee_cost": "0.083000", "player": "PULIS", "team": "USA", "stat": "assists", "line": 1.5}, {"market_ticker": "KXWCAST-26JUL01USABIH-USASDEST8-1", "side": "no", "price": 80, "contracts": 4.82, "created_time": "2026-07-01T22:51:47+00:00", "created_ms": 1782946307214, "is_taker": false, "fee_cost": "0.000000", "player": "DEST", "team": "USA", "stat": "assists", "line": 0.5}, {"market_ticker": "KXWCAST-26JUL01USABIH-USASDEST8-1", "side": "no", "price": 80, "contracts": 5.0, "created_time": "2026-07-01T22:51:30+00:00", "created_ms": 1782946290445, "is_taker": false, "fee_cost": "0.000000", "player": "DEST", "team": "USA", "stat": "assists", "line": 0.5}, {"market_ticker": "KXWCGOAL-26JUL01USABIH-BIHIBASIC13-1", "side": "no", "price": 95, "contracts": 187.4, "created_time": "2026-07-01T22:51:28+00:00", "created_ms": 1782946288982, "is_taker": false, "fee_cost": "0.000000", "player": "BASIC", "team": "BIH", "stat": "goals", "line": 0.5}, {"market_ticker": "KXWCAST-26JUL01USABIH-USASDEST8-1", "side": "no", "price": 80, "contracts": 113.59, "created_time": "2026-07-01T22:51:23+00:00", "created_ms": 1782946283565, "is_taker": false, "fee_cost": "0.000000", "player": "DEST", "team": "USA", "stat": "assists", "line": 0.5}, {"market_ticker": "KXWCGOAL-26JUL01USABIH-BIHAMEMIC99-1", "side": "no", "price": 94, "contracts": 52.14, "created_time": "2026-07-01T22:51:14+00:00", "created_ms": 1782946274421, "is_taker": false, "fee_cost": "0.000000", "player": "MEMIC", "team": "BIH", "stat": "goals", "line": 0.5}, {"market_ticker": "KXWCGOAL-26JUL01USABIH-BIHIBASIC13-1", "side": "no", "price": 95, "contracts": 187.52, "created_time": "2026-07-01T22:51:10+00:00", "created_ms": 1782946270113, "is_taker": false, "fee_cost": "0.000000", "player": "BASIC", "team": "BIH", "stat": "goals", "line": 0.5}, {"market_ticker": "KXWCAST-26JUL01USABIH-USASDEST8-1", "side": "no", "price": 80, "contracts": 20.0, "created_time": "2026-07-01T22:50:50+00:00", "created_ms": 1782946250221, "is_taker": false, "fee_cost": "0.000000", "player": "DEST", "team": "USA", "stat": "assists", "line": 0.5}, {"market_ticker": "KXWCAST-26JUL01USABIH-USASDEST8-1", "side": "no", "price": 80, "contracts": 22.0, "created_time": "2026-07-01T22:50:16+00:00", "created_ms": 1782946216521, "is_taker": false, "fee_cost": "0.000000", "player": "DEST", "team": "USA", "stat": "assists", "line": 0.5}, {"market_ticker": "KXWCAST-26JUL01USABIH-USAWMCKEN22-2", "side": "no", "price": 95, "contracts": 160.0, "created_time": "2026-07-01T22:50:01+00:00", "created_ms": 1782946201575, "is_taker": false, "fee_cost": "0.000000", "player": "MCKEN", "team": "USA", "stat": "assists", "line": 1.5}, {"market_ticker": "KXWCGOAL-26JUL01USABIH-BIHIBASIC13-1", "side": "no", "price": 95, "contracts": 18.75, "created_time": "2026-07-01T22:49:54+00:00", "created_ms": 1782946194301, "is_taker": false, "fee_cost": "0.000000", "player": "BASIC", "team": "BIH", "stat": "goals", "line": 0.5}, {"market_ticker": "KXWCAST-26JUL01USABIH-USAWMCKEN22-1", "side": "no", "price": 76, "contracts": 33.43, "created_time": "2026-07-01T22:49:01+00:00", "created_ms": 1782946141105, "is_taker": false, "fee_cost": "0.000000", "player": "MCKEN", "team": "USA", "stat": "assists", "line": 0.5}, {"market_ticker": "KXWCAST-26JUL01USABIH-USAWMCKEN22-1", "side": "no", "price": 76, "contracts": 7.65, "created_time": "2026-07-01T22:48:41+00:00", "created_ms": 1782946121199, "is_taker": false, "fee_cost": "0.000000", "player": "MCKEN", "team": "USA", "stat": "assists", "line": 0.5}, {"market_ticker": "KXWCGOAL-26JUL01USABIH-USASDEST8-1", "side": "no", "price": 85, "contracts": 112.32, "created_time": "2026-07-01T22:47:50+00:00", "created_ms": 1782946070537, "is_taker": false, "fee_cost": "0.000000", "player": "DEST", "team": "USA", "stat": "goals", "line": 0.5}, {"market_ticker": "KXWCAST-26JUL01USABIH-USAWMCKEN22-1", "side": "no", "price": 76, "contracts": 39.0, "created_time": "2026-07-01T22:47:09+00:00", "created_ms": 1782946029658, "is_taker": false, "fee_cost": "0.000000", "player": "MCKEN", "team": "USA", "stat": "assists", "line": 0.5}, {"market_ticker": "KXWCGOAL-26JUL01USABIH-USASDEST8-1", "side": "no", "price": 85, "contracts": 157.3, "created_time": "2026-07-01T22:47:08+00:00", "created_ms": 1782946028989, "is_taker": false, "fee_cost": "0.000000", "player": "DEST", "team": "USA", "stat": "goals", "line": 0.5}, {"market_ticker": "KXWCGOAL-26JUL01USABIH-USASDEST8-1", "side": "no", "price": 85, "contracts": 125.84, "created_time": "2026-07-01T22:47:05+00:00", "created_ms": 1782946025055, "is_taker": false, "fee_cost": "0.000000", "player": "DEST", "team": "USA", "stat": "goals", "line": 0.5}, {"market_ticker": "KXWCAST-26JUL01USABIH-USAWMCKEN22-1", "side": "no", "price": 76, "contracts": 7.91, "created_time": "2026-07-01T22:46:58+00:00", "created_ms": 1782946018540, "is_taker": false, "fee_cost": "0.000000", "player": "MCKEN", "team": "USA", "stat": "assists", "line": 0.5}, {"market_ticker": "KXWCGOAL-26JUL01USABIH-USASDEST8-1", "side": "no", "price": 85, "contracts": 34.92, "created_time": "2026-07-01T22:46:50+00:00", "created_ms": 1782946010080, "is_taker": false, "fee_cost": "0.000000", "player": "DEST", "team": "USA", "stat": "goals", "line": 0.5}, {"market_ticker": "KXWCGOAL-26JUL01USABIH-USASDEST8-1", "side": "no", "price": 85, "contracts": 31.46, "created_time": "2026-07-01T22:46:43+00:00", "created_ms": 1782946003458, "is_taker": false, "fee_cost": "0.000000", "player": "DEST", "team": "USA", "stat": "goals", "line": 0.5}, {"market_ticker": "KXWCGOAL-26JUL01USABIH-USASDEST8-1", "side": "no", "price": 85, "contracts": 18.87, "created_time": "2026-07-01T22:46:40+00:00", "created_ms": 1782946000809, "is_taker": false, "fee_cost": "0.000000", "player": "DEST", "team": "USA", "stat": "goals", "line": 0.5}, {"market_ticker": "KXWCGOAL-26JUL01USABIH-USASDEST8-1", "side": "no", "price": 85, "contracts": 6.29, "created_time": "2026-07-01T22:46:35+00:00", "created_ms": 1782945995903, "is_taker": false, "fee_cost": "0.000000", "player": "DEST", "team": "USA", "stat": "goals", "line": 0.5}, {"market_ticker": "KXWCAST-26JUL01USABIH-USASDEST8-1", "side": "no", "price": 80, "contracts": 14.2, "created_time": "2026-07-01T22:44:16+00:00", "created_ms": 1782945856441, "is_taker": false, "fee_cost": "0.000000", "player": "DEST", "team": "USA", "stat": "assists", "line": 0.5}, {"market_ticker": "KXWCAST-26JUL01USABIH-USASDEST8-1", "side": "no", "price": 80, "contracts": 13.0, "created_time": "2026-07-01T22:43:34+00:00", "created_ms": 1782945814355, "is_taker": false, "fee_cost": "0.000000", "player": "DEST", "team": "USA", "stat": "assists", "line": 0.5}, {"market_ticker": "KXWCAST-26JUL01USABIH-USASDEST8-1", "side": "no", "price": 80, "contracts": 68.0, "created_time": "2026-07-01T22:43:12+00:00", "created_ms": 1782945792071, "is_taker": false, "fee_cost": "0.000000", "player": "DEST", "team": "USA", "stat": "assists", "line": 0.5}, {"market_ticker": "KXWCAST-26JUL01USABIH-USAWMCKEN22-1", "side": "no", "price": 76, "contracts": 7.91, "created_time": "2026-07-01T22:36:04+00:00", "created_ms": 1782945364928, "is_taker": false, "fee_cost": "0.000000", "player": "MCKEN", "team": "USA", "stat": "assists", "line": 0.5}, {"market_ticker": "KXWCAST-26JUL01USABIH-USAWMCKEN22-1", "side": "no", "price": 76, "contracts": 27.66, "created_time": "2026-07-01T22:35:50+00:00", "created_ms": 1782945350519, "is_taker": false, "fee_cost": "0.000000", "player": "MCKEN", "team": "USA", "stat": "assists", "line": 0.5}, {"market_ticker": "KXWCSOA-26JUL01USABIH-USAFBALOG9", "side": "yes", "price": 56, "contracts": 415.52, "created_time": "2026-07-01T22:25:55+00:00", "created_ms": 1782944755809, "is_taker": false, "fee_cost": "0.000000", "player": "BALOG", "team": "USA", "stat": "soa", "line": null}, {"market_ticker": "KXWCAST-26JUL01USABIH-USAAROBIN33-1", "side": "yes", "price": 13, "contracts": 23.61, "created_time": "2026-07-01T22:24:56+00:00", "created_ms": 1782944696913, "is_taker": false, "fee_cost": "0.000000", "player": "ROBIN", "team": "USA", "stat": "assists", "line": 0.5}, {"market_ticker": "KXWCSOA-26JUL01USABIH-BIHIBASIC13", "side": "no", "price": 90, "contracts": 178.58, "created_time": "2026-07-01T22:17:41+00:00", "created_ms": 1782944261131, "is_taker": false, "fee_cost": "0.000000", "player": "BASIC", "team": "BIH", "stat": "soa", "line": null}, {"market_ticker": "KXWCAST-26JUL01USABIH-USAWMCKEN22-1", "side": "no", "price": 76, "contracts": 48.42, "created_time": "2026-07-01T22:15:54+00:00", "created_ms": 1782944154036, "is_taker": false, "fee_cost": "0.000000", "player": "MCKEN", "team": "USA", "stat": "assists", "line": 0.5}, {"market_ticker": "KXWCSOA-26JUL01USABIH-USAFBALOG9", "side": "yes", "price": 56, "contracts": 84.0, "created_time": "2026-07-01T22:14:40+00:00", "created_ms": 1782944080380, "is_taker": false, "fee_cost": "0.000000", "player": "BALOG", "team": "USA", "stat": "soa", "line": null}, {"market_ticker": "KXWCSOA-26JUL01USABIH-USAFBALOG9", "side": "no", "price": 40, "contracts": 99.58, "created_time": "2026-07-01T22:11:29+00:00", "created_ms": 1782943889624, "is_taker": false, "fee_cost": "0.000000", "player": "BALOG", "team": "USA", "stat": "soa", "line": null}, {"market_ticker": "KXWCSOA-26JUL01USABIH-USAFBALOG9", "side": "no", "price": 40, "contracts": 24.31, "created_time": "2026-07-01T22:11:14+00:00", "created_ms": 1782943874608, "is_taker": false, "fee_cost": "0.000000", "player": "BALOG", "team": "USA", "stat": "soa", "line": null}, {"market_ticker": "KXWCSOA-26JUL01USABIH-USAFBALOG9", "side": "no", "price": 40, "contracts": 32.0, "created_time": "2026-07-01T22:10:39+00:00", "created_ms": 1782943839574, "is_taker": false, "fee_cost": "0.000000", "player": "BALOG", "team": "USA", "stat": "soa", "line": null}, {"market_ticker": "KXWCSOA-26JUL01USABIH-USAFBALOG9", "side": "no", "price": 40, "contracts": 6.0, "created_time": "2026-07-01T22:08:58+00:00", "created_ms": 1782943738728, "is_taker": false, "fee_cost": "0.000000", "player": "BALOG", "team": "USA", "stat": "soa", "line": null}, {"market_ticker": "KXWCSOA-26JUL01USABIH-USAFBALOG9", "side": "no", "price": 40, "contracts": 161.0, "created_time": "2026-07-01T22:07:10+00:00", "created_ms": 1782943630558, "is_taker": false, "fee_cost": "0.000000", "player": "BALOG", "team": "USA", "stat": "soa", "line": null}, {"market_ticker": "KXWCSOA-26JUL01USABIH-USAFBALOG9", "side": "no", "price": 40, "contracts": 31.79, "created_time": "2026-07-01T22:04:51+00:00", "created_ms": 1782943491682, "is_taker": false, "fee_cost": "0.000000", "player": "BALOG", "team": "USA", "stat": "soa", "line": null}, {"market_ticker": "KXWCSOA-26JUL01USABIH-USAFBALOG9", "side": "no", "price": 40, "contracts": 129.7, "created_time": "2026-07-01T22:03:59+00:00", "created_ms": 1782943439436, "is_taker": false, "fee_cost": "0.000000", "player": "BALOG", "team": "USA", "stat": "soa", "line": null}, {"market_ticker": "KXWCSOA-26JUL01USABIH-BIHIBASIC13", "side": "no", "price": 90, "contracts": 67.0, "created_time": "2026-07-01T22:03:53+00:00", "created_ms": 1782943433520, "is_taker": false, "fee_cost": "0.000000", "player": "BASIC", "team": "BIH", "stat": "soa", "line": null}, {"market_ticker": "KXWCAST-26JUL01USABIH-USAFBALOG9-1", "side": "no", "price": 81, "contracts": 6.05, "created_time": "2026-07-01T22:03:50+00:00", "created_ms": 1782943430282, "is_taker": false, "fee_cost": "0.000000", "player": "BALOG", "team": "USA", "stat": "assists", "line": 0.5}, {"market_ticker": "KXWCSOA-26JUL01USABIH-BIHIBASIC13", "side": "no", "price": 90, "contracts": 18.81, "created_time": "2026-07-01T22:03:50+00:00", "created_ms": 1782943430175, "is_taker": false, "fee_cost": "0.000000", "player": "BASIC", "team": "BIH", "stat": "soa", "line": null}, {"market_ticker": "KXWCSOA-26JUL01USABIH-USAFBALOG9", "side": "no", "price": 40, "contracts": 3.0, "created_time": "2026-07-01T22:03:31+00:00", "created_ms": 1782943411148, "is_taker": false, "fee_cost": "0.000000", "player": "BALOG", "team": "USA", "stat": "soa", "line": null}, {"market_ticker": "KXWCSOA-26JUL01USABIH-USAFBALOG9", "side": "no", "price": 40, "contracts": 11.0, "created_time": "2026-07-01T22:03:29+00:00", "created_ms": 1782943409170, "is_taker": false, "fee_cost": "0.000000", "player": "BALOG", "team": "USA", "stat": "soa", "line": null}, {"market_ticker": "KXWCSOA-26JUL01USABIH-USAFBALOG9", "side": "no", "price": 40, "contracts": 1.62, "created_time": "2026-07-01T22:02:35+00:00", "created_ms": 1782943355710, "is_taker": false, "fee_cost": "0.000000", "player": "BALOG", "team": "USA", "stat": "soa", "line": null}, {"market_ticker": "KXWCSOA-26JUL01USABIH-USAFBALOG9", "side": "no", "price": 41, "contracts": 180.83, "created_time": "2026-07-01T22:00:22+00:00", "created_ms": 1782943222051, "is_taker": false, "fee_cost": "0.000000", "player": "BALOG", "team": "USA", "stat": "soa", "line": null}, {"market_ticker": "KXWCSOA-26JUL01USABIH-USAFBALOG9", "side": "no", "price": 41, "contracts": 52.72, "created_time": "2026-07-01T21:59:34+00:00", "created_ms": 1782943174694, "is_taker": false, "fee_cost": "0.000000", "player": "BALOG", "team": "USA", "stat": "soa", "line": null}, {"market_ticker": "KXWCSOA-26JUL01USABIH-USAFBALOG9", "side": "no", "price": 41, "contracts": 0.69, "created_time": "2026-07-01T21:59:05+00:00", "created_ms": 1782943145640, "is_taker": false, "fee_cost": "0.000000", "player": "BALOG", "team": "USA", "stat": "soa", "line": null}, {"market_ticker": "KXWCAST-26JUL01USABIH-USAWMCKEN22-1", "side": "no", "price": 76, "contracts": 146.02, "created_time": "2026-07-01T21:57:49+00:00", "created_ms": 1782943069487, "is_taker": false, "fee_cost": "0.000000", "player": "MCKEN", "team": "USA", "stat": "assists", "line": 0.5}, {"market_ticker": "KXWCSOA-26JUL01USABIH-USAFBALOG9", "side": "no", "price": 41, "contracts": 8.0, "created_time": "2026-07-01T21:57:43+00:00", "created_ms": 1782943063960, "is_taker": false, "fee_cost": "0.000000", "player": "BALOG", "team": "USA", "stat": "soa", "line": null}, {"market_ticker": "KXWCSOA-26JUL01USABIH-USAFBALOG9", "side": "no", "price": 41, "contracts": 8.23, "created_time": "2026-07-01T21:56:58+00:00", "created_ms": 1782943018853, "is_taker": false, "fee_cost": "0.000000", "player": "BALOG", "team": "USA", "stat": "soa", "line": null}, {"market_ticker": "KXWCSOA-26JUL01USABIH-USAFBALOG9", "side": "no", "price": 41, "contracts": 49.42, "created_time": "2026-07-01T21:55:42+00:00", "created_ms": 1782942942447, "is_taker": false, "fee_cost": "0.000000", "player": "BALOG", "team": "USA", "stat": "soa", "line": null}, {"market_ticker": "KXWCSOA-26JUL01USABIH-USAFBALOG9", "side": "no", "price": 41, "contracts": 16.47, "created_time": "2026-07-01T21:55:41+00:00", "created_ms": 1782942941254, "is_taker": false, "fee_cost": "0.000000", "player": "BALOG", "team": "USA", "stat": "soa", "line": null}, {"market_ticker": "KXWCSOA-26JUL01USABIH-USAFBALOG9", "side": "yes", "price": 56, "contracts": 3.34, "created_time": "2026-07-01T21:53:59+00:00", "created_ms": 1782942839088, "is_taker": false, "fee_cost": "0.000000", "player": "BALOG", "team": "USA", "stat": "soa", "line": null}, {"market_ticker": "KXWCSOA-26JUL01USABIH-USAFBALOG9", "side": "no", "price": 41, "contracts": 81.0, "created_time": "2026-07-01T21:53:01+00:00", "created_ms": 1782942781261, "is_taker": false, "fee_cost": "0.000000", "player": "BALOG", "team": "USA", "stat": "soa", "line": null}], "simulation": {"combined": {"worst": -28009.68, "p1": -13021.419200000004, "p10": -5301.902000000002, "p25": -713.8275000000006, "p50": 4257.009999999997, "p75": 8824.649999999996, "p90": 12494.649999999996, "best": 16850.19, "mean": 3846.3366136499985, "p_profit": 71.829, "staked": 44890.43000000001, "n_sims": 1000000, "roi": {"worst": -62.39565983217357, "p1": -29.007116216084366, "p10": -11.810762338431601, "p25": -1.5901551845237403, "p50": 9.483112547596438, "p75": 19.658198863321193, "p90": 27.833660760211014, "best": 37.53626329709917, "mean": 8.568277500683326}}, "per_game": [{"game": "USA vs BIH", "tag": "USABIH", "n_positions": 19, "unresolved": [], "worst": -8751.02, "p1": -5622.469999999999, "p10": -3371.39, "p25": -2028.7400000000007, "p50": 487.4099999999995, "p75": 4465.41, "p90": 5472.610000000001, "best": 5916.15, "mean": 869.5386577899998, "p_profit": 53.7443, "staked": 10581.18, "n_sims": 1000000, "roi": {"worst": -82.70363040795071, "p1": -53.13651218484138, "p10": -31.862136359082825, "p25": -19.173097896453896, "p50": 4.606386055241471, "p75": 42.20143689078156, "p90": 51.720224020383355, "best": 55.912006033353556, "mean": 8.217785330086055}}, {"game": "BEL vs SEN", "tag": "BELSEN", "n_positions": 53, "unresolved": [], "worst": -23527.280000000002, "p1": -12190.15, "p10": -5213.72, "p25": -1014.0000000000002, "p50": 3732.5399999999972, "p75": 7792.569999999999, "p90": 10871.479999999998, "best": 10934.039999999999, "mean": 2976.797955859999, "p_profit": 69.9589, "staked": 34309.25000000001, "n_sims": 1000000, "roi": {"worst": -68.5741600297296, "p1": -35.53021415507479, "p10": -15.196251739691188, "p25": -2.9554711921712076, "p50": 10.879106946377425, "p75": 22.71273781851832, "p90": 31.68673171229332, "best": 31.869073209119982, "mean": 8.676371403805092}}], "unsimmable": [], "n_simmable_games": 2, "n_positions_simmed": 72, "selected_games": ["BELSEN", "ENGCOD", "USABIH"], "generated_at": "2026-07-01T20:01:34.270778+00:00"}}